Workbook

Sheet Banco de preguntas
A1: ID | B1: Bloque | C1: Artículo/Regla | D1: Enunciado | E1: Opción A | F1: Opción B | G1: Opción C | H1: Correcta | I1: Explicación | J1: Referencia | K1: Fuente | L1: Dificultad | M1: Página
A2: BC-001 | B2: normativa | C2: Art. 20 | D2: Según las Bases de Competición, ¿qué obligación tiene el club local respecto a la asistencia sanitaria en cada partido? | E2: Disponer de un médico colegiado en plantilla y una ambulancia de soporte vital básico. | F2: Disponer únicamente de un fisioterapeuta en el banquillo local. | G2: Disponer de una ambulancia solo cuando lo solicite el equipo visitante. | H2: A | I2: El Artículo 20 exige médico colegiado obligatorio presente como local y ambulancia de soporte vital básico aportada por el club local. | J2: Art. 20 | K2: Resumen_Articulos_Bases_Competicion_20-30.pdf | L2: 4
A3: BC-002 | B3: normativa | C3: Art. 20 | D3: ¿Quién es responsable, entre otras funciones, del control antidopaje según el Artículo 20 de las Bases de Competición? | E3: El delegado de campo. | F3: El médico colegiado de la plantilla. | G3: El cuarto árbitro. | H3: B | I3: El médico colegiado obligatorio en plantilla es responsable, entre otras cosas, del control antidopaje. | J3: Art. 20 | K3: Resumen_Articulos_Bases_Competicion_20-30.pdf | L3: 1
A4: BC-003 | B4: normativa | C4: Art. 23 | D4: ¿Cuál es el número mínimo de futbolistas de la plantilla de la categoría necesario para poder empezar un partido según el Artículo 23 de las Bases de Competición? | E4: 7 futbolistas. | F4: 8 futbolistas. | G4: 9 futbolistas. | H4: A | I4: El Artículo 23 exige un mínimo de 7 futbolistas de la plantilla de la categoría para poder empezar el partido; en caso contrario, incomparecencia. | J4: Art. 23 | K4: Resumen_Articulos_Bases_Competicion_20-30.pdf | L4: 2
A5: BC-004 | B5: normativa | C5: Art. 23 | D5: Durante un partido, ¿cuántos futbolistas como máximo pueden no pertenecer a la plantilla de la categoría en que militan, según el Artículo 23 de las Bases de Competición? | E5: 2 futbolistas. | F5: 4 futbolistas. | G5: 6 futbolistas. | H5: B | I5: El Artículo 23 fija un máximo de 4 futbolistas que no pertenezcan a la plantilla de la categoría durante el partido. | J5: Art. 23 | K5: Resumen_Articulos_Bases_Competicion_20-30.pdf | L5: 4
A6: BC-005 | B6: normativa | C6: Art. 23 | D6: Si un equipo se presenta con menos de 7 futbolistas de su plantilla de categoría, ¿qué situación se produce según el Artículo 23 de las Bases de Competición? | E6: Se retrasa el inicio 30 minutos. | F6: Incomparecencia. | G6: Se juega igualmente con autorización del árbitro. | H6: B | I6: El mínimo de 7 futbolistas de la plantilla de la categoría es requisito para empezar; de no cumplirse, se considera incomparecencia. | J6: Art. 23 | K6: Resumen_Articulos_Bases_Competicion_20-30.pdf | L6: 4
A7: BC-006 | B7: normativa | C7: Art. 24 | D7: ¿Cuál es el número máximo de suplentes posibles según el Artículo 24 de las Bases de Competición? | E7: 7 suplentes. | F7: 9 suplentes. | G7: 12 suplentes. | H7: B | I7: El Artículo 24 establece un máximo de 9 suplentes posibles. | J7: Art. 24 | K7: Resumen_Articulos_Bases_Competicion_20-30.pdf | L7: 1
A8: BC-007 | B8: normativa | C8: Art. 24 | D8: ¿Cuántas sustituciones efectivas como máximo, y en cuántas interrupciones por equipo, permite el Artículo 24 de las Bases de Competición? | E8: 3 sustituciones en 2 interrupciones. | F8: 5 sustituciones en 3 interrupciones. | G8: 6 sustituciones en 4 interrupciones. | H8: B | I8: El Artículo 24 permite máximo 5 sustituciones efectivas, distribuidas en 3 interrupciones por equipo, previa autorización arbitral. | J8: Art. 24 | K8: Resumen_Articulos_Bases_Competicion_20-30.pdf | L8: 2
A9: BC-008 | B9: normativa | C9: Art. 24 | D9: En el Play Off de Ascenso, si el partido llega a la prórroga, ¿qué sustituciones adicionales contempla el Artículo 24 de las Bases de Competición? | E9: 2 sustituciones adicionales y 2 oportunidades más. | F9: 1 sustitución adicional y 1 oportunidad de sustitución más. | G9: No se permite ninguna sustitución adicional en prórroga. | H9: B | I9: En Play Off de Ascenso y Torneo de Permanencia, si hay prórroga se concede 1 sustitución adicional y 1 oportunidad de sustitución más. | J9: Art. 24 | K9: Resumen_Articulos_Bases_Competicion_20-30.pdf | L9: 4
A10: BC-009 | B10: normativa | C10: Art. 24 | D10: ¿Cuántos futbolistas como máximo pueden calentar por equipo en banda junto al preparador físico, según el Artículo 24 de las Bases de Competición? | E10: 3 futbolistas. | F10: 5 futbolistas. | G10: 7 futbolistas. | H10: B | I10: El Artículo 24 fija un máximo de 5 futbolistas por equipo calentando en banda junto al preparador físico. | J10: Art. 24 | K10: Resumen_Articulos_Bases_Competicion_20-30.pdf | L10: 2
A11: BC-010 | B11: normativa | C11: Art. 24 | D11: ¿Se puede sustituir a un futbolista que ha sido expulsado, según el Artículo 24 de las Bases de Competición? | E11: Sí, siempre que queden sustituciones disponibles. | F11: No, en ningún caso. | G11: Sí, pero solo en la segunda parte. | H11: B | I11: El Artículo 24 establece expresamente que no se puede sustituir a un futbolista expulsado. | J11: Art. 24 | K11: Resumen_Articulos_Bases_Competicion_20-30.pdf | L11: 4
A12: BC-011 | B12: normativa | C12: Art. 24 | D12: ¿Quién puede acceder al vestuario según el Artículo 24 de las Bases de Competición? | E12: Cualquier aficionado o socio acreditado por el club, sin ninguna restricción adicional. | F12: Solo miembros autorizados: equipo arbitral, futbolistas inscritos en acta, técnicos, médicos, fisioterapeutas, delegados, etc. | G12: Únicamente los capitanes de ambos equipos y el delegado de campo del club local. | H12: B | I12: El Artículo 24 limita el acceso al vestuario a los miembros autorizados expresamente enumerados. | J12: Art. 24 | K12: Resumen_Articulos_Bases_Competicion_20-30.pdf | L12: 2
A13: BC-012 | B13: normativa | C13: Art. 25 | D13: ¿A qué normativa de juego están sujetos obligatoriamente los partidos según el Artículo 25 de las Bases de Competición? | E13: A las Reglas de Juego de la IFAB vigentes en la temporada en curso. | F13: A las Reglas de Juego que decida cada federación autonómica. | G13: A un reglamento propio de la RFEF independiente de la IFAB. | H13: A | I13: El Artículo 25 establece la sujeción obligatoria a las Reglas de Juego de la IFAB vigentes en la temporada en curso. | J13: Art. 25 | K13: Resumen_Articulos_Bases_Competicion_20-30.pdf | L13: 4
... A93: RC-041 | B93: normativa | C93: Art. 150 | D93: ¿Cuántas personas como máximo puede haber en el banquillo técnico adicional, situado a 5 metros del principal, según el Artículo 150 del Reglamento de Competiciones? | E93: 3 personas. | F93: 5 personas. | G93: 7 personas. | H93: B | I93: El Artículo 150 fija un máximo de 5 personas en el banquillo técnico adicional, situado a 5 metros del principal. | J93: Art. 150 | K93: ResumenReglamentoCompeticiones.pdf | L93: 2
A94: RC-042 | B94: normativa | C94: Art. 150 | D94: Un futbolista es expulsado. Según el Artículo 150 del Reglamento de Competiciones: | E94: Debe dirigirse a los vestuarios, sin poder presenciar el partido desde la grada. | F94: Puede presenciar el resto del partido desde la grada de público. | G94: Puede permanecer en el banquillo, mientras no intervenga en el juego. | H94: A | I94: Art. 150.5: «Los que resulten ser expulsados/as, deberán dirigirse a los vestuarios sin posibilidad de presenciar el partido desde la grada». La excepción afecta solo a médicos, Graduado/a en Enfermería y fisioterapeuta, que no pueden seguir en el banquillo pero sí presenciar el partido. | J94: Art. 150 | K94: ReglamentoDeCompeticiones2025.pdf | L94: 4 | M94: 124
A95: RC-043 | B95: normativa | C95: Art. 151 | D95: ¿Quién no puede ejercer como delegado de campo, según el Artículo 151 del Reglamento de Competiciones? | E95: Un miembro de la Junta Directiva de la RFEF. | F95: El entrenador titular del equipo local. | G95: Cualquier futbolista suplente. | H95: A | I95: El Artículo 151 prohíbe que sea delegado de campo un miembro de la Junta Directiva de la RFEF. | J95: Art. 151 | K95: ResumenReglamentoCompeticiones.pdf | L95: 1
A96: RC-044 | B96: normativa | C96: Art. 153 | D96: ¿Puede el Presidente del club actuar como delegado según el Artículo 153 del Reglamento de Competiciones? | E96: Sí, es una función habitual que puede asumir el Presidente del club. | F96: No, no puede actuar como delegado el/la Presidente/a o Consejero/a Delegado/a del club. | G96: Sí, siempre que lo autorice expresamente el árbitro antes del partido. | H96: B | I96: El Artículo 153 prohíbe que el Presidente o Consejero Delegado del club actúe como delegado, ni tampoco un miembro de la Junta Directiva de la RFEF. | J96: Art. 153 | K96: ResumenReglamentoCompeticiones.pdf | L96: 2
A97: RC-045 | B97: normativa | C97: Art. 154 | D97: ¿Qué obligación tienen los capitanes respecto al acta, según el Artículo 154 del Reglamento de Competiciones? | E97: Firmar la primera parte del acta antes del comienzo del partido. | F97: Redactar personalmente el informe de incidencias. | G97: No tienen ninguna obligación relacionada con el acta. | H97: A | I97: El Artículo 154 exige que los capitanes firmen la primera parte del acta antes del comienzo del partido. | J97: Art. 154 | K97: ResumenReglamentoCompeticiones.pdf | L97: 2
A98: RC-046 | B98: normativa | C98: Art. 155 | D98: Según el Artículo 155 del Reglamento de Competiciones, ¿cuándo empiezan y terminan las facultades del árbitro? | E98: Empiezan al pitar el inicio y terminan al pitar el final, sin incluir descansos. | F98: Empiezan al entrar en el recinto y no terminan hasta que lo abandona, incluidos descansos y suspensiones. | G98: Solo tiene facultades mientras el balón está en juego. | H98: B | I98: El Artículo 155 establece que las facultades del árbitro empiezan al entrar en el recinto y no terminan hasta que lo abandona, incluyendo descansos y suspensiones. | J98: Art. 155 | K98: ResumenReglamentoCompeticiones.pdf | L98: 3
A99: RC-047 | B99: normativa | C99: Art. 155 | D99: Si el árbitro principal no puede continuar el partido, ¿quién lo sustituye según el Artículo 155 del Reglamento de Competiciones? | E99: El cuarto árbitro automáticamente. | F99: El asistente de superior categoría arbitral. | G99: Se suspende el partido obligatoriamente. | H99: B | I99: El Artículo 155 establece que si el árbitro no puede continuar, lo sustituye el asistente de superior categoría arbitral. | J99: Art. 155 | K99: ResumenReglamentoCompeticiones.pdf | L99: 2
A100: RC-048 | B100: normativa | C100: Art. 156 | D100: Según el Artículo 156 del Reglamento de Competiciones, ¿cuántas personas pueden estar en el terreno de juego sin autorización, sumando futbolistas y equipo arbitral? | E100: 22 futbolistas más árbitros asistentes y 4º árbitro. | F100: 20 futbolistas más árbitros asistentes únicamente. | G100: 24 futbolistas más todo el equipo técnico. | H100: A | I100: El Artículo 156 permite en el terreno de juego a 22 futbolistas más árbitros asistentes y 4º árbitro, sin autorización de nadie más. | J100: Art. 156 | K100: ResumenReglamentoCompeticiones.pdf | L100: 3
A101: RC-049 | B101: normativa | C101: Art. 158 | D101: ¿Con qué antelación mínima debe personarse el equipo arbitral en el campo, según el Artículo 158 del Reglamento de Competiciones? | E101: Una hora. | F101: Hora y media. | G101: Dos horas. | H101: B | I101: El Artículo 158 exige que el equipo arbitral se persone en el campo con una antelación mínima de hora y media. | J101: Art. 158 | K101: ResumenReglamentoCompeticiones.pdf | L101: 1
A102: RC-050 | B102: normativa | C102: Art. 175 | D102: ¿En qué categorías es obligatoria la ambulancia según el Artículo 175 del Reglamento de Competiciones? | E102: Solo en 1ª y 2ª División, sin exigirse en el resto de categorías. | F102: En campos de 1ª/2ª Federación, 1ª/2ª Fed. Femenina y 1ª División de Fútbol Sala. | G102: En todas las categorías sin excepción, incluidas las categorías inferiores. | H102: B | I102: El Artículo 175 exige ambulancia obligatoria en campos de 1ª/2ª Federación, 1ª/2ª Federación Femenina y 1ª División de Fútbol Sala. | J102: Art. 175 | K102: ResumenReglamentoCompeticiones.pdf | L102: 3
A103: RC-051 | B103: normativa | C103: Art. 175 | D103: ¿Qué está prohibido sobre el terreno de juego, marcos/redes de porterías y banderines de córner durante el partido, según el Artículo 175 del Reglamento de Competiciones? | E103: Toda publicidad, sin excepción alguna en esos elementos del terreno de juego. | F103: Únicamente la publicidad de bebidas alcohólicas y tabaco, no el resto. | G103: No hay ninguna restricción publicitaria sobre esos elementos del terreno. | H103: A | I103: El Artículo 175 prohíbe toda publicidad sobre el terreno de juego, marcos/redes de porterías y banderines de córner durante el partido. | J103: Art. 175 | K103: ResumenReglamentoCompeticiones.pdf | L103: 4
A104: RC-052 | B104: normativa | C104: Art. 183 | D104: ¿Qué logotipo es obligatorio en las prendas deportivas fuera de las competiciones profesionales, según el Artículo 183 del Reglamento de Competiciones? | E104: El logotipo de la Liga Profesional. | F104: El logotipo de la RFEF. | G104: No es obligatorio ningún logotipo institucional. | H104: B | I104: El Artículo 183 exige el logotipo de la Liga Profesional en competiciones profesionales y de la RFEF en el resto de categorías. | J104: Art. 183 | K104: ResumenReglamentoCompeticiones.pdf | L104: 3
A105: RC-053 | B105: normativa | C105: Art. 184 | D105: ¿Qué tipo de publicidad está prohibida en las prendas deportivas según el Artículo 184 del Reglamento de Competiciones? | E105: La de bebidas alcohólicas o tabaco. | F105: La de marcas de material deportivo. | G105: La de entidades bancarias. | H105: A | I105: El Artículo 184 prohíbe anunciar bebidas alcohólicas o tabaco, y prohíbe alterar los colores o emblemas del club. | J105: Art. 184 | K105: ResumenReglamentoCompeticiones.pdf | L105: 1
A106: RC-054 | B106: normativa | C106: Art. 185 | D106: ¿A partir de qué tamaño se considera publicidad la marca del fabricante de la prenda, según el Artículo 185 del Reglamento de Competiciones? | E106: A partir de 10 cm². | F106: A partir de 15 cm². | G106: A partir de 20 cm². | H106: B | I106: El Artículo 185 establece que no se considera publicidad la marca del fabricante si no excede 15 cm² en conjunto. | J106: Art. 185 | K106: ResumenReglamentoCompeticiones.pdf | L106: 2
... A232: RC-196 | B232: normativa | C232: Art. 133 | D232: Según el Artículo 133 del Reglamento de Competiciones, ¿a partir de qué momento se considera a un equipo no comparecido? | E232: Si transcurren 30 minutos desde la hora fijada sin presentarse o con jugadores insuficientes. | F232: Si transcurren 15 minutos desde la hora fijada sin presentarse. | G232: Si transcurre 1 hora desde la hora fijada sin presentarse. | H232: A | I232: El Artículo 133 considera no comparecido a un equipo si transcurren 30 minutos desde la hora fijada sin presentarse o con jugadores insuficientes. | J232: Art. 133 | K232: ResumenReglamentoCompeticiones.pdf | L232: 2
A233: RJ1-001 | B233: reglas | C233: Regla 1 | D233: Durante un partido en el que se utiliza el VAR, un miembro del cuerpo técnico intenta comunicarse por radio con el AVAR sin estar autorizado para ello. ¿Qué establece la Regla 1 al respecto? | E233: Que solo las personas autorizadas podrán entrar en la sala de vídeo o comunicarse con el VAR, el AVAR o el técnico de repeticiones. | F233: Que solo las personas autorizadas podrán entrar en la sala de vídeo, pudiendo comunicarse con el VAR, el AVAR o el técnico de repeticiones los miembros del cuerpo técnico. | G233: Que solo las personas autorizadas podrán comunicarse con el VAR, el AVAR o el técnico de repeticiones, pudiendo entrar en la sala de vídeo los miembros del cuerpo técnico. | H233: A | I233: Durante el partido, únicamente las personas autorizadas podrán entrar en la sala de vídeo o comunicarse con el VAR, el AVAR o el técnico de repeticiones. | J233: Regla 1 / Árbitros asistentes de vídeo (VAR) | K233: ReglasDelJuego26-27.pdf | L233: 2 | M233: 29
A234: RJ1-002 | B234: reglas | C234: Regla 1 | D234: ¿Qué establece la Regla 1 sobre el cumplimiento de un programa de calidad para las porterías empleadas en competiciones oficiales auspiciadas por la FIFA o las confederaciones? | E234: Se recomienda que cumplan los criterios del Programa de calidad de la FIFA de porterías de fútbol. | F234: Es obligatorio que cumplan los criterios del Programa de calidad de la FIFA de porterías de fútbol. | G234: No existe ninguna referencia normativa sobre programas de calidad para las porterías. | H234: A | I234: La Regla 1 recomienda, sin imponerlo como obligación, que las porterías empleadas en competiciones oficiales auspiciadas por la FIFA o las confederaciones cumplan los criterios del Programa de calidad de la FIFA de porterías de fútbol. | J234: Regla 1 / Porterías | K234: ReglasDelJuego26-27.pdf | L234: 2 | M234: 27
A235: RJ1-003 | B235: reglas | C235: Regla 1 | D235: ¿Cómo describe la Regla 1 la composición de una portería respecto a los postes de los banderines de esquina? | E235: Dos postes verticales equidistantes de los postes de los banderines de esquina, unidos por un travesaño horizontal. | F235: Dos postes verticales situados a la misma distancia entre sí que los postes de los banderines de esquina. | G235: Dos postes verticales alineados con los postes de los banderines de esquina, sin travesaño obligatorio. | H235: A | I235: Una portería consta de dos postes verticales, equidistantes de los postes de los banderines de esquina y unidos en la parte superior por un travesaño horizontal. | J235: Regla 1 / Porterías | K235: ReglasDelJuego26-27.pdf | L235: 2 | M235: 27
A236: RJ1-004 | B236: reglas | C236: Regla 1 | D236: Un club fabrica los postes de su portería con un material no homologado que, además, resulta peligroso para los jugadores. ¿Qué exige la Regla 1 sobre los materiales de postes y travesaño? | E236: Que estén fabricados con materiales homologados y no constituyan ningún peligro. | F236: Que estén fabricados con materiales homologados, aunque puedan suponer cierto riesgo si el club lo asume. | G236: Que el material sea decidido libremente por el club, sin exigencia de homologación. | H236: A | I236: Los postes y el travesaño deberán estar fabricados con materiales homologados y no deberán constituir ningún peligro. | J236: Regla 1 / Porterías | K236: ReglasDelJuego26-27.pdf | L236: 2 | M236: 27
A237: RJ1-005 | B237: reglas | C237: Regla 1 | D237: ¿En qué momento debe el árbitro comprobar el correcto funcionamiento de la DAG, según la Regla 1? | E237: Antes del partido, según lo estipulado en el manual de pruebas. | F237: Antes del partido, salvo que el árbitro lo considere innecesario, según lo estipulado en el manual de pruebas. | G237: Durante el descanso, antes de iniciar la segunda parte, según lo estipulado en el manual de pruebas. | H237: A | I237: Cuando se vaya a hacer uso de la DAG, el árbitro deberá comprobar su correcto funcionamiento antes del partido, según se estipula en el manual de pruebas. | J237: Regla 1 / Detección automática de goles | K237: ReglasDelJuego26-27.pdf | L237: 2 | M237: 29
A238: RJ1-006 | B238: reglas | C238: Regla 1 | D238: Si se utiliza la DAG en competición, ¿a qué deben extenderse las garantías exigidas a los organizadores sobre el cumplimiento del Programa de calidad de la FIFA? | E238: Al sistema completo, incluidos los posibles cambios autorizados en los marcos de las porterías o en la tecnología usada en los balones. | F238: Al dispositivo instalado en la línea de meta, incluidos los posibles cambios autorizados en los marcos de las porterías, pero no a la tecnología usada en los balones. | G238: Al sistema completo, excluidos los posibles cambios autorizados en los marcos de las porterías o en la tecnología usada en los balones. | H238: A | I238: Los organizadores deberán garantizar que el sistema, incluidos los posibles cambios autorizados en los marcos de las porterías o en la tecnología usada en los balones, cumpla con los requisitos del Programa de calidad de la FIFA. | J238: Regla 1 / Detección automática de goles | K238: ReglasDelJuego26-27.pdf | L238: 3 | M238: 29
A239: RJ1-007 | B239: reglas | C239: Regla 1 | D239: ¿Hasta cuándo se prohíbe la publicidad comercial en el terreno de juego una vez finalizado el descanso, según la Regla 1? | E239: Desde que los equipos vuelven a entrar en el terreno de juego hasta el término del partido. | F239: Desde que los equipos vuelven a entrar en el terreno de juego hasta que se reanuda el juego. | G239: Desde que se reanuda el juego tras el descanso hasta el término del partido. | H239: A | I239: La prohibición de publicidad rige también desde el momento en que los equipos vuelven a entrar en el terreno de juego hasta el término del partido. | J239: Regla 1 / Publicidad comercial | K239: ReglasDelJuego26-27.pdf | L239: 2 | M239: 29
A240: RJ1-008 | B240: reglas | C240: Regla 1 | D240: ¿A qué tipo de partidos se relaciona particularmente el área técnica, según la Regla 1? | E240: A los disputados en estadios que cuentan con un área específica con asientos para el cuerpo técnico, los suplentes y los jugadores sustituidos. | F240: A los disputados en estadios que cuentan con un área específica con asientos para el cuerpo técnico y los suplentes, con exclusión de los jugadores sustituidos. | G240: A los disputados en competiciones internacionales organizadas por la FIFA en estadios que cuentan con un área específica con asientos. | H240: A | I240: El área técnica se relaciona en particular con los partidos disputados en estadios que cuentan con un área específica con asientos para el cuerpo técnico, los suplentes y los jugadores sustituidos. | J240: Regla 1 / Área técnica | K240: ReglasDelJuego26-27.pdf | L240: 2 | M240: 27
A241: RJ1-010 | B241: reglas | C241: Regla 1 | D241: Un club solicita disputar sus partidos sobre una superficie completamente artificial. ¿Es posible según la Regla 1? | E241: Sí, siempre que lo permita el reglamento de la competición. | F241: No, la superficie completamente artificial solo se permite si lo autoriza la FIFA para cada partido. | G241: Sí, siempre que lo permita el árbitro antes del inicio de cada partido. | H241: A | I241: La Regla 1 permite una superficie completamente artificial si lo autoriza el reglamento de la competición. | J241: Regla 1 / Superficie de juego | K241: ReglasDelJuego26-27.pdf | L241: 1 | M241: 25
A242: RJ1-011 | B242: reglas | C242: Regla 1 | D242: Un campo combina césped natural con fibras artificiales integradas en el mismo terreno. ¿Qué condición exige la Regla 1 para que este sistema híbrido sea válido? | E242: Que el reglamento de la competición lo permita expresamente. | F242: Que lo autorice el árbitro antes de cada partido concreto. | G242: Que el club lo comunique a la federación con 15 días de antelación. | H242: A | I242: La combinación integrada de materiales artificiales y naturales (sistema híbrido) requiere que el reglamento de la competición lo permita. | J242: Regla 1 / Superficie de juego | K242: ReglasDelJuego26-27.pdf | L242: 3 | M242: 25
A243: RJ1-013 | B243: reglas | C243: Regla 1 | D243: En partidos internacionales de competición de clubes disputados sobre superficie artificial, ¿qué debe cumplir dicha superficie según la Regla 1? | E243: Los requisitos del Programa de calidad de la FIFA de césped artificial, salvo dispensa especial del IFAB. | F243: Los requisitos del Programa de calidad de la FIFA de césped artificial, salvo dispensa especial de la federación anfitriona. | G243: Los requisitos que determine la federación anfitriona del partido, salvo dispensa especial del IFAB. | H243: A | I243: Las superficies artificiales en partidos internacionales de clubes deben cumplir el Programa de calidad de la FIFA de césped artificial, salvo dispensa del IFAB. | J243: Regla 1 / Superficie de juego | K243: ReglasDelJuego26-27.pdf | L243: 3 | M243: 25
A244: RJ1-016 | B244: reglas | C244: Regla 1 | D244: En una superficie artificial coexisten las líneas de demarcación de fútbol con las de otro deporte. ¿Qué exige la Regla 1 para que esto sea admisible? | E244: Que las líneas del otro deporte sean de un color diferente y se distingan claramente de las de fútbol. | F244: Que las líneas del otro deporte se borren antes de cada partido de fútbol. | G244: Que ambos deportes utilicen exactamente el mismo grosor de línea para evitar confusión. | H244: A | I244: En superficies artificiales se permite la coexistencia con otras líneas siempre que sean de color diferente y se distingan claramente de las de fútbol. | J244: Regla 1 / Marcación del terreno | K244: ReglasDelJuego26-27.pdf | L244: 3 | M244: 25
... A1391: VAR-058 | B1391: reglas | C1391: Protocolo del VAR | D1391: ¿Puede modificarse, durante el propio partido, la decisión de utilizar o no el sistema VAR ya anunciada antes de su inicio? | E1391: No, se determina antes del partido conforme a los requisitos exigidos, salvo avería del sistema. | F1391: Sí, cualquiera de los dos equipos puede pedir activar o desactivar el VAR durante el partido. | G1391: Sí, el árbitro puede decidir libremente activar el VAR en el segundo tiempo. | H1391: A | I1391: La implementación del VAR se decide antes del inicio del partido conforme a los requisitos técnicos exigidos, sin que pueda modificarse a mitad de encuentro salvo por causas técnicas como una avería. | J1391: Protocolo del VAR | K1391: ReglasDelJuego26-27.pdf | L1391: 2 | M1391: 87

Sheet Resumen Reglas
A1: Regla / Tema | B1: Nº preguntas
A2: Regla 1 | B2: =COUNTIF('Banco de preguntas'!$C:$C,"Regla 1") -> 97
A3: Regla 2 | B3: =COUNTIF('Banco de preguntas'!$C:$C,"Regla 2") -> 32
A4: Regla 3 | B4: =COUNTIF('Banco de preguntas'!$C:$C,"Regla 3") -> 88
A5: Regla 4 | B5: =COUNTIF('Banco de preguntas'!$C:$C,"Regla 4") -> 77
A6: Regla 5 | B6: =COUNTIF('Banco de preguntas'!$C:$C,"Regla 5") -> 81
A7: Regla 6 | B7: =COUNTIF('Banco de preguntas'!$C:$C,"Regla 6") -> 48
A8: Regla 7 | B8: =COUNTIF('Banco de preguntas'!$C:$C,"Regla 7") -> 38
A9: Regla 8 | B9: =COUNTIF('Banco de preguntas'!$C:$C,"Regla 8") -> 39
A10: Regla 9 | B10: =COUNTIF('Banco de preguntas'!$C:$C,"Regla 9") -> 30
A11: Regla 10 | B11: =COUNTIF('Banco de preguntas'!$C:$C,"Regla 10") -> 51
A12: Regla 11 | B12: =COUNTIF('Banco de preguntas'!$C:$C,"Regla 11") -> 61
A13: Regla 12 | B13: =COUNTIF('Banco de preguntas'!$C:$C,"Regla 12") -> 202
A14: Regla 13 | B14: =COUNTIF('Banco de preguntas'!$C:$C,"Regla 13") -> 45
A15: Regla 14 | B15: =COUNTIF('Banco de preguntas'!$C:$C,"Regla 14") -> 56
A16: Regla 15 | B16: =COUNTIF('Banco de preguntas'!$C:$C,"Regla 15") -> 42
A17: Regla 16 | B17: =COUNTIF('Banco de preguntas'!$C:$C,"Regla 16") -> 28
A18: Regla 17 | B18: =COUNTIF('Banco de preguntas'!$C:$C,"Regla 17") -> 24
A19: Glosario | B19: =COUNTIF('Banco de preguntas'!$C:$C,"Glosario") -> 63
A20: VAR | B20: =COUNTIF('Banco de preguntas'!$C:$C,"VAR")+COUNTIF('Banco de preguntas'!$C:$C,"Protocolo del VAR") -> 57
A21: Normativa (Reglamento y Bases) | B21: =COUNTIF('Banco de preguntas'!$B:$B,"normativa") -> 231
A22: TOTAL | B22: =SUM(B2:B21) -> 1390

Sheet Regla 1
A1: ID | B1: Tipo | C1: Enunciado | D1: Opción A | E1: Opción B | F1: Opción C | G1: Correcta | H1: Explicación | I1: Referencia | J1: Dificultad
A2: RJ1-001 | B2: situacion | C2: Durante un partido en el que se utiliza el VAR, un miembro del cuerpo técnico intenta comunicarse por radio con el AVAR sin estar autorizado para ello. ¿Qué establece la Regla 1 al respecto? | D2: Que solo las personas autorizadas podrán entrar en la sala de vídeo o comunicarse con el VAR, el AVAR o el técnico de repeticiones. | E2: Que solo las personas autorizadas podrán entrar en la sala de vídeo, pudiendo comunicarse con el VAR, el AVAR o el técnico de repeticiones los miembros del cuerpo técnico. | F2: Que solo las personas autorizadas podrán comunicarse con el VAR, el AVAR o el técnico de repeticiones, pudiendo entrar en la sala de vídeo los miembros del cuerpo técnico. | G2: A | H2: Durante el partido, únicamente las personas autorizadas podrán entrar en la sala de vídeo o comunicarse con el VAR, el AVAR o el técnico de repeticiones. | I2: Regla 1 / Árbitros asistentes de vídeo (VAR) | J2: 2
A3: RJ1-002 | B3: directa | C3: ¿Qué establece la Regla 1 sobre el cumplimiento de un programa de calidad para las porterías empleadas en competiciones oficiales auspiciadas por la FIFA o las confederaciones? | D3: Se recomienda que cumplan los criterios del Programa de calidad de la FIFA de porterías de fútbol. | E3: Es obligatorio que cumplan los criterios del Programa de calidad de la FIFA de porterías de fútbol. | F3: No existe ninguna referencia normativa sobre programas de calidad para las porterías. | G3: A | H3: La Regla 1 recomienda, sin imponerlo como obligación, que las porterías empleadas en competiciones oficiales auspiciadas por la FIFA o las confederaciones cumplan los criterios del Programa de calidad de la FIFA de porterías de fútbol. | I3: Regla 1 / Porterías | J3: 2
A4: RJ1-003 | B4: directa | C4: ¿Cómo describe la Regla 1 la composición de una portería respecto a los postes de los banderines de esquina? | D4: Dos postes verticales equidistantes de los postes de los banderines de esquina, unidos por un travesaño horizontal. | E4: Dos postes verticales situados a la misma distancia entre sí que los postes de los banderines de esquina. | F4: Dos postes verticales alineados con los postes de los banderines de esquina, sin travesaño obligatorio. | G4: A | H4: Una portería consta de dos postes verticales, equidistantes de los postes de los banderines de esquina y unidos en la parte superior por un travesaño horizontal. | I4: Regla 1 / Porterías | J4: 2
A5: RJ1-004 | B5: situacion | C5: Un club fabrica los postes de su portería con un material no homologado que, además, resulta peligroso para los jugadores. ¿Qué exige la Regla 1 sobre los materiales de postes y travesaño? | D5: Que estén fabricados con materiales homologados y no constituyan ningún peligro. | E5: Que estén fabricados con materiales homologados, aunque puedan suponer cierto riesgo si el club lo asume. | F5: Que el material sea decidido libremente por el club, sin exigencia de homologación. | G5: A | H5: Los postes y el travesaño deberán estar fabricados con materiales homologados y no deberán constituir ningún peligro. | I5: Regla 1 / Porterías | J5: 2
A6: RJ1-005 | B6: directa | C6: ¿En qué momento debe el árbitro comprobar el correcto funcionamiento de la DAG, según la Regla 1? | D6: Antes del partido, según lo estipulado en el manual de pruebas. | E6: Antes del partido, salvo que el árbitro lo considere innecesario, según lo estipulado en el manual de pruebas. | F6: Durante el descanso, antes de iniciar la segunda parte, según lo estipulado en el manual de pruebas. | G6: A | H6: Cuando se vaya a hacer uso de la DAG, el árbitro deberá comprobar su correcto funcionamiento antes del partido, según se estipula en el manual de pruebas. | I6: Regla 1 / Detección automática de goles | J6: 2
A7: RJ1-006 | B7: situacion | C7: Si se utiliza la DAG en competición, ¿a qué deben extenderse las garantías exigidas a los organizadores sobre el cumplimiento del Programa de calidad de la FIFA? | D7: Al sistema completo, incluidos los posibles cambios autorizados en los marcos de las porterías o en la tecnología usada en los balones. | E7: Al dispositivo instalado en la línea de meta, incluidos los posibles cambios autorizados en los marcos de las porterías, pero no a la tecnología usada en los balones. | F7: Al sistema completo, excluidos los posibles cambios autorizados en los marcos de las porterías o en la tecnología usada en los balones. | G7: A | H7: Los organizadores deberán garantizar que el sistema, incluidos los posibles cambios autorizados en los marcos de las porterías o en la tecnología usada en los balones, cumpla con los requisitos del Programa de calidad de la FIFA. | I7: Regla 1 / Detección automática de goles | J7: 3
A8: RJ1-007 | B8: directa | C8: ¿Hasta cuándo se prohíbe la publicidad comercial en el terreno de juego una vez finalizado el descanso, según la Regla 1? | D8: Desde que los equipos vuelven a entrar en el terreno de juego hasta el término del partido. | E8: Desde que los equipos vuelven a entrar en el terreno de juego hasta que se reanuda el juego. | F8: Desde que se reanuda el juego tras el descanso hasta el término del partido. | G8: A | H8: La prohibición de publicidad rige también desde el momento en que los equipos vuelven a entrar en el terreno de juego hasta el término del partido. | I8: Regla 1 / Publicidad comercial | J8: 2
A9: RJ1-008 | B9: directa | C9: ¿A qué tipo de partidos se relaciona particularmente el área técnica, según la Regla 1? | D9: A los disputados en estadios que cuentan con un área específica con asientos para el cuerpo técnico, los suplentes y los jugadores sustituidos. | E9: A los disputados en estadios que cuentan con un área específica con asientos para el cuerpo técnico y los suplentes, con exclusión de los jugadores sustituidos. | F9: A los disputados en competiciones internacionales organizadas por la FIFA en estadios que cuentan con un área específica con asientos. | G9: A | H9: El área técnica se relaciona en particular con los partidos disputados en estadios que cuentan con un área específica con asientos para el cuerpo técnico, los suplentes y los jugadores sustituidos. | I9: Regla 1 / Área técnica | J9: 2
A10: RJ1-010 | B10: situacion | C10: Un club solicita disputar sus partidos sobre una superficie completamente artificial. ¿Es posible según la Regla 1? | D10: Sí, siempre que lo permita el reglamento de la competición. | E10: No, la superficie completamente artificial solo se permite si lo autoriza la FIFA para cada partido. | F10: Sí, siempre que lo permita el árbitro antes del inicio de cada partido. | G10: A | H10: La Regla 1 permite una superficie completamente artificial si lo autoriza el reglamento de la competición. | I10: Regla 1 / Superficie de juego | J10: 1
A11: RJ1-011 | B11: situacion | C11: Un campo combina césped natural con fibras artificiales integradas en el mismo terreno. ¿Qué condición exige la Regla 1 para que este sistema híbrido sea válido? | D11: Que el reglamento de la competición lo permita expresamente. | E11: Que lo autorice el árbitro antes de cada partido concreto. | F11: Que el club lo comunique a la federación con 15 días de antelación. | G11: A | H11: La combinación integrada de materiales artificiales y naturales (sistema híbrido) requiere que el reglamento de la competición lo permita. | I11: Regla 1 / Superficie de juego | J11: 3
A12: RJ1-013 | B12: situacion | C12: En partidos internacionales de competición de clubes disputados sobre superficie artificial, ¿qué debe cumplir dicha superficie según la Regla 1? | D12: Los requisitos del Programa de calidad de la FIFA de césped artificial, salvo dispensa especial del IFAB. | E12: Los requisitos del Programa de calidad de la FIFA de césped artificial, salvo dispensa especial de la federación anfitriona. | F12: Los requisitos que determine la federación anfitriona del partido, salvo dispensa especial del IFAB. | G12: A | H12: Las superficies artificiales en partidos internacionales de clubes deben cumplir el Programa de calidad de la FIFA de césped artificial, salvo dispensa del IFAB. | I12: Regla 1 / Superficie de juego | J12: 3
A13: RJ1-016 | B13: situacion | C13: En una superficie artificial coexisten las líneas de demarcación de fútbol con las de otro deporte. ¿Qué exige la Regla 1 para que esto sea admisible? | D13: Que las líneas del otro deporte sean de un color diferente y se distingan claramente de las de fútbol. | E13: Que las líneas del otro deporte se borren antes de cada partido de fútbol. | F13: Que ambos deportes utilicen exactamente el mismo grosor de línea para evitar confusión. | G13: A | H13: En superficies artificiales se permite la coexistencia con otras líneas siempre que sean de color diferente y se distingan claramente de las de fútbol. | I13: Regla 1 / Marcación del terreno | J13: 3
... A98: RJ1-114 | B98: situacion | C98: Un terreno de juego cuenta con césped híbrido, que combina fibras naturales y artificiales entrelazadas. ¿Se ajusta esto a lo que permite la Regla 1 sobre el tipo de superficie? | D98: Sí, el terreno de juego puede ser de césped natural, artificial o una combinación de ambos, lo que incluye sistemas híbridos, siempre que lo permita el reglamento de la competición. | E98: No, un sistema híbrido no está contemplado entre los tipos de superficie que permite la Regla 1, que solo admite césped natural o artificial de forma independiente. | F98: Sí, sin que sea necesaria ninguna autorización del reglamento de la competición para este tipo concreto de superficie. | G98: A | H98: La Regla 1 permite que el terreno de juego sea de césped natural, artificial o una combinación de ambos (lo que incluye los sistemas híbridos), siempre que lo permita el reglamento de la competición. | I98: Regla 1 | J98: 3

Sheet Regla 2
A1: ID | B1: Tipo | C1: Enunciado | D1: Opción A | E1: Opción B | F1: Opción C | G1: Correcta | H1: Explicación | I1: Referencia | J1: Dificultad
A2: RJ2-001 | B2: directa | C2: ¿Pueden los capitanes proponer al árbitro el cambio de balón durante el transcurso del juego? | D2: Sí, pero será potestad del árbitro atender o no la petición. | E2: Sí, y el árbitro está obligado a comprobarlo y cambiarlo. | F2: No, el balón solo puede cambiarse por iniciativa del árbitro. | G2: A | H2: Los capitanes pueden proponer el cambio de balón, pero corresponde al árbitro decidir si atiende o no dicha petición. | I2: Regla 2 | J2: 1
A3: RJ2-003 | B3: directa | C3: ¿Cuál es la circunferencia reglamentaria del balón? | D3: Entre 68 y 70 cm. | E3: Entre 64 y 66 cm. | F3: Entre 70 y 72 cm. | G3: A | H3: La circunferencia del balón debe estar comprendida entre 68 y 70 cm. | I3: Regla 2 / Características y medidas | J3: 1
A4: RJ2-004 | B4: directa | C4: ¿Cuál es el peso reglamentario del balón al comienzo del partido? | D4: Entre 410 y 450 g. | E4: Entre 400 y 440 g. | F4: Entre 420 y 460 g. | G4: A | H4: El balón debe tener un peso comprendido entre 410 y 450 g al comienzo del partido. | I4: Regla 2 / Características y medidas | J4: 1
A5: RJ2-005 | B5: directa | C5: ¿Cuál es la presión reglamentaria del balón al nivel del mar? | D5: Entre 0,6 y 1,1 atmósferas. | E5: Entre 0,4 y 0,9 atmósferas. | F5: Entre 1,0 y 1,5 atmósferas. | G5: A | H5: La presión del balón debe ser equivalente a 0,6–1,1 atmósferas al nivel del mar. | I5: Regla 2 / Características y medidas | J5: 2
A6: RJ2-006 | B6: situacion | C6: Un delegado presenta un balón cuyo peso al inicio del partido es de 405 g, dentro de una circunferencia de 69 cm. ¿Es reglamentario? | D6: No, porque el peso no alcanza el mínimo de 410 g exigido al comienzo del partido. | E6: Sí, porque el peso solo se exige a partir de la segunda parte del encuentro. | F6: Sí, porque la circunferencia está dentro del rango permitido y basta con ello. | G6: A | H6: El balón debe pesar entre 410 y 450 g al comienzo del partido; con 405 g queda por debajo del mínimo exigido. | I6: Regla 2 / Características y medidas | J6: 3
A7: RJ2-007 | B7: situacion | C7: En partidos de competición oficial organizados bajo los auspicios de la FIFA o las confederaciones, ¿qué deben cumplir los balones utilizados? | D7: Los criterios del Programa de calidad de la FIFA de balones de fútbol y portar uno de sus sellos de calidad. | E7: Los criterios del Programa de calidad de la FIFA de balones de fútbol, sin necesidad de portar ningún sello de calidad. | F7: Los criterios que fije cada federación nacional de fútbol y portar uno de sus sellos de calidad. | G7: A | H7: Todos los balones utilizados en partidos de competición oficial de la FIFA o confederaciones deben cumplir los criterios del Programa de calidad de la FIFA de balones de fútbol y portar uno de sus sellos de calidad. | I7: Regla 2 / Características y medidas | J7: 3
A8: RJ2-008 | B8: directa | C8: ¿Qué indican los distintivos o sellos de calidad que puede portar un balón? | D8: Que el balón ha sido examinado oficialmente y cumple los requisitos técnicos mínimos estipulados en la Regla 2. | E8: Que el balón ha sido examinado oficialmente y cumple los requisitos técnicos máximos estipulados en la Regla 2. | F8: Que el balón ha sido fabricado en un país autorizado por la FIFA y cumple los requisitos técnicos mínimos de la Regla 2. | G8: A | H8: Estos distintivos indican que el balón ha sido examinado oficialmente y cumple los requisitos técnicos mínimos estipulados en la Regla 2 y aprobados por el IFAB. | I8: Regla 2 / Características y medidas | J8: 3
A9: RJ2-009 | B9: directa | C9: ¿Pueden las federaciones nacionales de fútbol exigir en sus competiciones el uso de balones con sello de calidad? | D9: Sí, en las competiciones de las federaciones nacionales se podrá exigir el uso de balones que lleven uno de estos distintivos. | E9: No, esa exigencia está reservada a la FIFA y a las confederaciones continentales de fútbol. | F9: Sí, en las competiciones de las federaciones nacionales de categorías profesionales masculinas de máximo nivel. | G9: A | H9: En las competiciones de las federaciones nacionales de fútbol, se podrá exigir el uso de balones que lleven uno de estos distintivos de calidad. | I9: Regla 2 / Características y medidas | J9: 2
A10: RJ2-010 | B10: situacion | C10: En un partido de competición oficial bajo los auspicios de una federación nacional, ¿qué publicidad comercial está permitida en el balón? | D10: El logotipo o emblema de la competición o su organizador, y la marca registrada autorizada del fabricante. | E10: El logotipo o emblema de la competición o su organizador, y el de los patrocinadores del club local. | F10: El logotipo o emblema de la federación nacional, y la marca registrada autorizada del fabricante. | G10: A | H10: Está prohibida toda publicidad comercial en el balón, con excepción del logotipo o emblema de la competición o su organizador y la marca registrada autorizada del fabricante. | I10: Regla 2 / Características y medidas | J10: 3
A11: RJ2-011 | B11: directa | C11: ¿Quién puede restringir el tamaño y el número de las marcas autorizadas del fabricante en el balón? | D11: El reglamento de la competición. | E11: El fabricante del balón. | F11: El árbitro principal, antes del inicio de cada partido. | G11: A | H11: El reglamento de la competición podrá restringir el tamaño y el número de dichas marcas. | I11: Regla 2 / Características y medidas | J11: 2
A12: RJ2-012 | B12: situacion | C12: Durante el juego habitual, el balón pierde sus propiedades y no puede seguir utilizándose. ¿Qué debe hacer el árbitro? | D12: Detener el juego y reanudarlo con un balón a tierra. | E12: Detener el juego y reanudarlo con un saque de banda a favor del equipo que tenía la posesión. | F12: Permitir que el juego continúe hasta la siguiente interrupción natural. | G12: A | H12: Si el balón perdiera sus propiedades y no pudiera seguir utilizándose, se detendrá el juego y se reanudará con un balón a tierra. | I12: Regla 2 / Sustitución de un balón defectuoso | J12: 1
A13: RJ2-015 | B13: situacion | C13: Durante la ejecución de un tiro penal, el balón queda defectuoso mientras se desplaza hacia adelante, antes de tocar a ningún jugador, el poste o el travesaño, y el guardameta llega a detenerlo. ¿Qué decisión toma el árbitro? | D13: Ordena repetir el lanzamiento. | E13: Concede un balón a tierra al guardameta. | F13: Concede un saque de meta. | G13: A | H13: Si el balón queda defectuoso en el lanzamiento de un tiro penal (o de la tanda de penales) mientras se desplaza hacia adelante, antes de tocar a un jugador, el poste o el travesaño, se vuelve a ejecutar el lanzamiento, con independencia de que el guardameta lo detenga. | I13: Regla 2 / Sustitución de un balón defectuoso | J13: 3
... A33: RJ2-045 | B33: situacion | C33: En una competición no organizada bajo los auspicios de la FIFA ni de las confederaciones, un club presenta un balón sin sello de calidad que cumple las especificaciones de la Regla 2. ¿Puede utilizarse? | D33: Sí, salvo que el reglamento de esa competición exija el sello de calidad. | E33: No, todo balón de competición oficial debe llevar un sello de calidad. | F33: No, sin sello de calidad el balón se considera defectuoso. | G33: A | H33: Portar uno de los sellos de calidad no es una exigencia general para cualquier balón; solo se exige obligatoriamente en las competiciones oficiales de la FIFA o las confederaciones, y de forma potestativa en las de las federaciones nacionales que así lo decidan. | I33: Regla 2 | J33: 3

Sheet Regla 3
A1: ID | B1: Tipo | C1: Enunciado | D1: Opción A | E1: Opción B | F1: Opción C | G1: Correcta | H1: Explicación | I1: Referencia | J1: Dificultad
A2: RJ3-001 | B2: situacion | C2: Un suplente entra en el terreno de juego sin permiso del árbitro y marca un gol; el árbitro se da cuenta antes de que se reanude el juego. El árbitro... | D2: Anula el gol, amonesta al suplente y reanuda con tiro libre directo en el lugar de la interferencia. | E2: Anula el gol, amonesta al suplente y reanuda con tiro libre directo desde el área de meta. | F2: Anula el gol, amonesta al suplente y reanuda con balón a tierra desde el área de meta. | G2: A | H2: Entrar al terreno de juego sin autorización del árbitro se sanciona con amonestación, anulación del gol si procede, y tiro libre directo a favor del equipo defensor desde el lugar donde se produjo la interferencia. | I2: Regla 3 | J2: 4
A3: RJ3-002 | B3: situacion | C3: Un jugador que va a ser sustituido se niega a abandonar el terreno de juego. El árbitro... | D3: Lo amonesta por conducta antideportiva. | E3: Lo amonesta por retrasar la reanudación del juego. | F3: No toma medida disciplinaria y el partido continúa. | G3: C | H3: Regla 3 (pág. 34): «si un jugador que debe ser sustituido se negara a salir del terreno de juego, el partido continuará». | I3: Regla 3 | J3: 2
A4: RJ3-003 | B4: situacion | C4: El preparador físico, situado en la zona de calentamiento, detiene el balón antes de que salga del campo, sin intención de interferir en el juego. ¿Qué decisión toma el árbitro? | D4: Tiro libre directo o penal a favor del equipo contrario, y expulsión del preparador físico. | E4: Tiro libre indirecto en el lugar de la infracción, sin amonestación. | F4: Tiro libre directo o penal a favor del equipo contrario, y amonestación al preparador físico por entrar al terreno de juego sin permiso. | G4: B | H4: Detener el balón sin intención de interferir, desde fuera del terreno, se sanciona con tiro libre indirecto en el lugar de la infracción, sin sanción disciplinaria si no hubo intención de interferir. | I4: Regla 3 / Regla 12 | J4: 4
A5: RJ3-004 | B5: situacion | C5: Un equipo presenta solo nueve jugadores nombrados en el saque inicial. ¿Pueden incorporarse al partido los dos jugadores que faltaban una vez comenzado? | D5: Sí, siempre que el árbitro conociera sus nombres antes del comienzo y las reglas de la competición lo permitan. | E5: No, deben estar presentes antes del comienzo del encuentro, sin excepción prevista en las Reglas de Juego. | F5: Sí, siempre que el árbitro conociera sus nombres antes del comienzo, aunque las reglas de la competición no lo permitan. | G5: A | H5: Los jugadores pueden incorporarse una vez comenzado el partido si el árbitro conocía sus nombres previamente y el reglamento de la competición lo permite. | I5: Regla 3 | J5: 3
A6: RJ3-005 | B6: situacion | C6: Un jugador incluido en la lista del equipo es expulsado mientras realiza el calentamiento, 20 minutos antes del comienzo del partido. ¿Qué ocurre? | D6: El equipo empieza el partido con un jugador menos. | E6: No se puede expulsar a ningún jugador antes del saque inicial. | F6: En su lugar juega un suplente, y no se cuenta como sustitución. | G6: C | H6: Si la expulsión se produce antes del inicio del partido, el jugador expulsado puede ser reemplazado por un suplente sin que compute como sustitución. | I6: Regla 3 | J6: 3
A7: RJ3-006 | B7: situacion | C7: Un suplente que está calentando detrás de la portería entra al terreno de juego e impide con el pie una oportunidad manifiesta de gol. ¿Qué decisión toma el árbitro? | D7: Lo amonesta y reanuda con tiro libre directo o penal. | E7: Lo expulsa y reanuda con tiro libre directo o penal. | F7: Lo expulsa y reanuda con tiro libre indirecto. | G7: B | H7: Impedir una ocasión manifiesta de gol mediante la entrada ilegal de un suplente se sanciona con expulsión y tiro libre directo o penal según el lugar de la infracción. | I7: Regla 3 / Regla 12 | J7: 2
A8: RJ3-007 | B8: directa | C8: ¿Puede comenzar un partido un equipo con menos de 7 jugadores? | D8: No, el partido no puede comenzar con menos de 7 jugadores. | E8: Sí, si lo permite el reglamento de la competición. | F8: Sí, en partidos amistosos. | G8: A | H8: La Regla 3 exige un mínimo de 7 jugadores por equipo para poder comenzar el partido, sin excepciones por tipo de competición. | I8: Regla 3 | J8: 1
A9: RJ3-008 | B9: situacion | C9: Un guardameta y un jugador de campo intercambian su puesto sin avisar al árbitro. ¿Qué decisión toma el árbitro? | D9: Permite que el juego continúe y apercibe verbalmente a ambos cuando el balón deje de estar en juego. | E9: Permite que el juego continúe y amonesta a ambos cuando el balón deje de estar en juego. | F9: Detiene el juego, reanuda con tiro libre indirecto y amonesta a ambos por el cambio no autorizado. | G9: B | H9: El intercambio de puesto entre guardameta y jugador de campo sin autorización se sanciona, en la siguiente interrupción, con amonestación a ambos jugadores, sin necesidad de detener el juego en el momento. | I9: Regla 3 | J9: 3
A10: RJ3-009 | B10: directa | C10: ¿Cuál es el número mínimo de futbolistas necesario, según la Regla 3, para que un equipo pueda continuar un partido ya iniciado sin darlo por finalizado? | D10: 6 jugadores. | E10: 7 jugadores. | F10: 8 jugadores. | G10: B | H10: El mínimo de 7 jugadores exigido para iniciar un partido es también el umbral por debajo del cual el partido no puede continuar. | I10: Regla 3 | J10: 2
A11: RJ3-010 | B11: situacion | C11: El árbitro inspecciona el equipamiento del suplente a la altura de la línea de medio campo antes de permitir una sustitución. ¿Cuándo empieza a contar el plazo de diez segundos del sustituido? | D11: Cuando la inspección haya terminado y el árbitro indique que se efectúe la sustitución. | E11: Cuando el árbitro comienza a inspeccionar el equipamiento del suplente. | F11: Cuando el cuarto árbitro muestra el tablero, aunque la inspección no haya concluido. | G11: A | H11: Según el protocolo del límite de tiempo en las sustituciones, si el árbitro inspecciona el equipamiento del suplente en la línea de medio campo, los diez segundos empiezan cuando la inspección ha terminado y el árbitro indica que se efectúe la sustitución. | I11: Regla 3.3 / Procedimiento de sustitución | J11: 3
A12: RJ3-011 | B12: situacion | C12: Un jugador sustituido se encuentra muy cerca de la línea de banda, cruzándola, cuando el árbitro termina la cuenta atrás de cinco segundos del plazo de diez. ¿Qué decide el árbitro? | D12: Permite que el suplente entre en el terreno de juego. | E12: No permite que el suplente entre hasta que transcurra un minuto desde la reanudación. | F12: Amonesta al jugador sustituido por retrasar la reanudación. | G12: A | H12: Como la finalidad de la cuenta atrás es impedir pérdidas de tiempo, si el jugador sustituido está muy cerca de la línea o cruzándola al terminar la cuenta, se permite que el suplente entre. | I12: Regla 3.3 / Procedimiento de sustitución | J12: 3
A13: RJ3-013 | B13: situacion | C13: Durante una sustitución, ¿por dónde debe entrar el jugador suplente al terreno de juego, con carácter general? | D13: Por la línea de banda a la altura de la línea media, tras recibir la señal del árbitro, salvo excepciones autorizadas por él. | E13: Por cualquier punto de la línea de banda, tras recibir la señal del árbitro, salvo excepciones autorizadas por él. | F13: Por la zona donde se encuentre el banquillo de su equipo, sin necesidad de señal del árbitro. | G13: A | H13: Con carácter general, el suplente solo puede entrar al terreno de juego por la línea de banda a la altura de la línea media (línea central), tras recibir la señal del árbitro, salvo que este autorice otra ubicación. | I13: Regla 3 | J13: 2
... A89: RJ3-093 | B89: directa | C89: ¿Puede un jugador de campo intercambiar su puesto con el guardameta durante una interrupción del juego sin informar antes al árbitro? | D89: No, debe informarse al árbitro antes de que se produzca el cambio. | E89: Sí, si el cambio se realiza durante una interrupción del juego. | F89: Sí, si se informa al árbitro en la siguiente interrupción del juego. | G89: A | H89: El intercambio de puesto entre un jugador de campo y el guardameta requiere comunicación previa e informar al árbitro antes de que se produzca. | I89: Regla 3 | J89: 2

Sheet Regla 4
A1: ID | B1: Tipo | C1: Enunciado | D1: Opción A | E1: Opción B | F1: Opción C | G1: Correcta | H1: Explicación | I1: Referencia | J1: Dificultad
A2: RJ3-012 | B2: directa | C2: ¿Es obligatorio que el capitán de un equipo lleve un brazalete distintivo? | D2: Sí, es una obligación general, pero su diseño puede quedar sujeto al reglamento de la competición. | E2: Sí, en todas las categorías, con un diseño fijado por las Reglas de Juego. | F2: No es obligatorio, quedando su uso a la libre elección de cada capitán antes del partido. | G2: A | H2: El capitán debe llevar un brazalete distintivo; su diseño concreto (colores, inscripciones) puede quedar sujeto a lo que autorice el reglamento de cada competición. | I2: Regla 4 | J2: 1
A3: RJ4-001 | B3: situacion | C3: Un jugador sale del terreno de juego para cambiarse la camiseta manchada de sangre. ¿Cuándo podrá volver al terreno de juego? | D3: Con permiso del árbitro, tras revisar su equipamiento un miembro del equipo arbitral, aunque el juego no esté detenido. | E3: Con permiso del árbitro, tras revisar su equipamiento un miembro del equipo arbitral, y solo con el juego detenido. | F3: En cuanto se cambie la camiseta, sin que sea necesario revisar su equipamiento ni el permiso del árbitro. | G3: A | H3: Regla 4 (pág. 40): el jugador debe someter el equipamiento al control de un miembro del equipo arbitral y volver a entrar únicamente con el permiso del árbitro, «el cual puede concederse durante el juego». | I3: Regla 4 | J3: 3
A4: RJ4-002 | B4: situacion | C4: Un jugador que había salido del terreno de juego para arreglar su camiseta manchada de sangre reingresa sin que el juego esté detenido y sin permiso del árbitro. ¿Qué decisión toma el árbitro? | D4: Amonesta al jugador y concede tiro libre indirecto en el lugar donde estaba el balón cuando se detiene el juego, salvo interferencia, en cuyo caso será directo o penal desde el lugar de la interferencia. | E4: Amonesta al jugador y concede tiro libre directo en el lugar donde estaba el balón cuando se detiene el juego, salvo interferencia, en cuyo caso será indirecto desde el lugar de la interferencia. | F4: Expulsa al jugador y concede tiro libre indirecto en el lugar donde estaba el balón cuando se detiene el juego, salvo interferencia, en cuyo caso será directo o penal desde el lugar de la interferencia. | G4: A | H4: Reingresar sin autorización conlleva amonestación y tiro libre indirecto donde estaba el balón al detenerse el juego, salvo que hubiera interferencia, que se sanciona con directo o penal desde el lugar de la interferencia. | I4: Regla 3 / Regla 4 | J4: 4
A5: RJ4-003 | B5: situacion | C5: Antes del partido, el delegado local comunica que el capitán llevará un brazalete con los colores de la bandera nacional y la letra 'C'. ¿Qué debe decidir el árbitro? | D5: Permitirlo si lo autoriza el reglamento de la competición. | E5: Permitirlo si cumple las estipulaciones de la Regla 4 sobre el equipamiento. | F5: No permitirlo, porque el brazalete debe ser de un solo color. | G5: A | H5: El uso de brazaletes de capitán con diseños o colores concretos queda sujeto a lo que permita el reglamento de la propia competición. | I5: Regla 4 | J5: 4
A6: RJ4-004 | B6: directa | C6: Según la Regla 4, los eslóganes, mensajes e imágenes autorizados deberán aparecer únicamente: | D6: En el frontal de la camiseta y del pantalón, o en el brazalete. | E6: En el frontal de la camiseta o en el brazalete. | F6: En el frontal del pantalón o en las mangas. | G6: B | H6: Regla 4 (pág. 39): «Los eslóganes autorizados, los mensajes y las imágenes deberán aparecer únicamente en el frontal de la camiseta o en el brazalete». | I6: Regla 4 | J6: 1
A7: RJ4-006 | B7: situacion | C7: Durante la revisión de indumentaria previa al partido, ¿puede el árbitro exigir que se retire un elemento no reglamentario del uniforme? | D7: Sí, forma parte de sus obligaciones inspeccionar la indumentaria de los jugadores antes del partido. | E7: No, esa función corresponde al delegado de campo de cada equipo antes del partido. | F7: No, la revisión de indumentaria corresponde al cuarto árbitro, no al árbitro principal. | G7: A | H7: Entre las obligaciones del árbitro antes del partido está inspeccionar el terreno, los balones y también verificar que el equipamiento de los jugadores cumple la normativa. | I7: Regla 4 / Regla 5 | J7: 3
A8: RJ4-007 | B8: situacion | C8: Un jugador sale al terreno de juego con unas espinilleras que no ofrecen un grado de protección razonable. El árbitro... | D8: No le permite participar hasta que corrija su equipamiento. | E8: Le permite participar, porque la elección de las espinilleras es libre. | F8: Le permite participar, pero lo amonesta por su equipamiento. | G8: A | H8: El árbitro debe verificar que el equipamiento obligatorio, incluidas las espinilleras, ofrece una protección razonable antes de permitir la participación del jugador. | I8: Regla 4 | J8: 2
A9: RJ4-008 | B9: directa | C9: ¿Puede un jugador llevar una camiseta interior de un color distinto a la manga principal de la camiseta de juego? | D9: Debe coincidir sustancialmente con el color principal de la manga de la camiseta. | E9: Puede ser de cualquier color, ya que las Reglas de Juego no regulan las prendas interiores. | F9: Está prohibida cualquier prenda interior bajo la camiseta. | G9: A | H9: La Regla 4 exige que la camiseta interior coincida, en su color principal, con el color dominante de la manga de la camiseta de juego. | I9: Regla 4 | J9: 2
A10: RJ4-009 | B10: situacion | C10: Durante una jugada, un jugador pierde accidentalmente la camiseta y sigue jugando. El árbitro... | D10: No detiene el juego; lo corregirá en la próxima detención. | E10: Detiene el juego de inmediato y amonesta al jugador. | F10: Detiene el juego de inmediato y concede tiro libre indirecto. | G10: A | H10: Regla 4.6: «En caso de infracción de esta regla, no es necesario detener el juego»; el árbitro ordenará al jugador que corrija su equipamiento y saldrá del terreno de juego cuando se detenga el juego, a menos que ya lo haya corregido. | I10: Regla 4.6 | J10: 1
A11: RJ4-011 | B11: situacion | C11: Un jugador quiere jugar con un accesorio que no es peligroso, cubierto de forma segura con cinta adhesiva. Según la Regla 4 (2026/27): | D11: Puede llevarlo. | E11: Debe quitárselo. | F11: Solo si la cinta es del color de la prenda. | G11: A | H11: Regla 4 (pág. 37): «Se permite llevar accesorios siempre y cuando no sean peligrosos y estén cubiertos de forma segura». Las prendas u objetos peligrosos sí deben quitarse: no basta con cubrirlos con cinta adhesiva. | I11: Regla 4 / Seguridad | J11: 2
A12: RJ4-013 | B12: situacion | C12: Un jugador lleva un accesorio prohibido y no puede o no quiere quitárselo cuando el árbitro se lo ordena. El árbitro... | D12: Le ordena que salga del terreno de juego en la próxima detención del juego. | E12: Le permite seguir jugando y lo hace constar en el acta del partido. | F12: Detiene el juego de inmediato y lo expulsa por no acatar su orden. | G12: A | H12: Si el jugador no puede o no quiere acatar la orden de quitarse el objeto, el árbitro deberá ordenarle que salga del terreno de juego en la próxima detención del juego. | I12: Regla 4 / Seguridad | J12: 2
A13: RJ4-014 | B13: situacion | C13: Un jugador se niega a quitarse un objeto peligroso cuando el árbitro se lo ordena, o vuelve a ponérselo tras haberlo retirado. ¿Qué sanción disciplinaria corresponde? | D13: Deberá ser amonestado, ya que negarse a acatar la orden constituye conducta antideportiva. | E13: Deberá ser expulsado, al tratarse de una reincidencia equivalente a una segunda amonestación en el mismo partido. | F13: No corresponde sanción disciplinaria alguna, solo debe salir del terreno. | G13: A | H13: Deberá amonestarse a todo jugador que rehúse acatar esta regla o que vuelva a ponerse el objeto o prenda prohibidos. | I13: Regla 4 / Seguridad | J13: 2
... A78: RJ4-085 | B78: situacion | C78: Los jugadores de un equipo lucen un eslogan de una iniciativa social contra una enfermedad que no es político, religioso, personal ni discriminatorio. ¿Está permitido con carácter general? | D78: Sí, los eslóganes de alguna iniciativa se permiten con carácter general. | E78: No, cualquier eslogan exige la autorización previa de la competición. | F78: No, una referencia a una enfermedad se considera de carácter personal. | G78: A | H78: Se permite, con carácter general, incluir en el equipamiento eslóganes de alguna iniciativa, siempre que respeten las condiciones generales fijadas por la Regla 4 (no político, religioso, personal ni discriminatorio, entre otras). | I78: Regla 4 | J78: 3

Sheet Regla 5
A1: ID | B1: Tipo | C1: Enunciado | D1: Opción A | E1: Opción B | F1: Opción C | G1: Correcta | H1: Explicación | I1: Referencia | J1: Dificultad
A2: RJ5-001 | B2: situacion | C2: Un guardameta hace marcas en el terreno de juego con el pie mientras el balón está en juego. El árbitro... | D2: Detiene el juego de inmediato y lo amonesta por conducta antideportiva. | E2: Lo amonesta por conducta antideportiva cuando el balón deje de estar en juego. | F2: Detiene el juego, lo amonesta y reanuda con un balón a tierra. | G2: B | H2: Regla 1 (pág. 26): si un jugador realiza marcas no autorizadas en el terreno de juego, será amonestado por conducta antideportiva; si el árbitro se percata durante el partido, lo amonestará en cuanto el balón deje de estar en juego. | I2: Regla 5 / Regla 12 | J2: 3
A3: RJ5-002 | B3: directa | C3: ¿Puede el árbitro modificar una decisión ya tomada mientras el balón sigue en juego? | D3: Sí, si se percata de un error, siempre que el juego no se haya reanudado o no haya finalizado el partido. | E3: No, una vez tomada una decisión no puede cambiarla, aunque el juego no se haya reanudado. | F3: Sí, si se percata de un error, siempre que el VAR se lo indique expresamente. | G3: A | H3: El árbitro puede modificar una decisión antes de la reanudación del juego (o antes de finalizar el partido en ciertos supuestos) si constata que fue incorrecta o se produjo mal informado. | I3: Regla 5 | J3: 1
A4: RJ5-003 | B4: situacion | C4: Durante el partido, el terreno de juego queda en mal estado. ¿Puede el árbitro suspender el partido? | D4: Sí, es una de las causas de suspensión previstas. | E4: No, una vez iniciado el partido debe terminarse. | F4: No, solo puede aplazarlo para otra fecha. | G4: A | H4: El mal estado del terreno de juego sobrevenido es una de las causas reconocidas para la suspensión del partido por decisión arbitral. | I4: Regla 5 / Reglamento de Competiciones | J4: 2
A5: RJ5-004 | B5: situacion | C5: Un club pide al árbitro que no refleje una incidencia en el acta del partido. El árbitro... | D5: Redacta el acta de forma fiel, concisa, clara, objetiva y completa. | E5: Puede omitir la incidencia si el club se lo solicita razonadamente. | F5: Puede matizar la incidencia si ambos clubes están de acuerdo. | G5: A | H5: El árbitro tiene la obligación de redactar el acta de forma fiel, concisa, clara, objetiva y completa, sin que las peticiones de los clubes puedan alterar ese deber. | I5: Regla 5 | J5: 2
A6: RJ5-005 | B6: situacion | C6: El árbitro detiene el juego por una lesión de un jugador de campo que es atendido en el terreno de juego por el cuerpo médico. No es una lesión de las excepciones. ¿Cuándo empieza a contar el minuto fuera del terreno de juego? | D6: En el momento en que se reanuda el juego. | E6: En el momento en que sale del campo. | F6: En el momento en que el árbitro autoriza la entrada del cuerpo médico. | G6: A | H6: El periodo de un minuto fuera del terreno de juego empieza a contar en el momento en que se reanuda el juego, con cronómetro y determinado por el árbitro. | I6: Protocolo médico / Un minuto fuera | J6: 3
A7: RJ5-006 | B7: situacion | C7: Un jugador de campo, lesionado, debe abandonar el campo y permanecer fuera un minuto tras la reanudación. Antes de que transcurra ese minuto finaliza la primera parte. ¿Qué ocurre? | D7: Puede regresar desde el comienzo de la segunda parte. | E7: Debe cumplir el minuto completo al inicio de la segunda parte antes de regresar. | F7: No podrá volver a participar en el partido. | G7: A | H7: Si la primera mitad finaliza antes de que transcurra el minuto, el jugador puede regresar desde el comienzo de la segunda parte (principio aplicable también entre tiempo reglamentario y prórroga, descanso de la prórroga y antes de tanda). | I7: Protocolo médico / Un minuto fuera | J7: 3
A8: RJ5-007 | B8: directa | C8: ¿Para qué tipo de decisiones podrán las competiciones usar tecnología que ayude al árbitro? | D8: Para el protocolo del VAR, el balón en juego (incluida la detección automática de goles) y el fuera de juego. | E8: Para el protocolo del VAR y las decisiones sobre conducta violenta fuera del terreno de juego. | F8: Para el control del tiempo de juego, las sustituciones y la validez de las tarjetas mostradas por el árbitro. | G8: A | H8: La tecnología puede ayudar al árbitro en el protocolo del VAR, el balón en juego (con DAG) y el fuera de juego. | I8: Regla 5.2 | J8: 2
A9: RJ5-008 | B9: directa | C9: ¿Son revocables las decisiones arbitrales sobre hechos y acciones sucedidos durante el encuentro, incluyendo dar por válido un gol? | D9: No, son irrevocables, y las decisiones del equipo arbitral deben respetarse en todo momento. | E9: Sí, pueden modificarse en cualquier momento si el árbitro recibe una indicación de un árbitro asistente. | F9: Sí, si ambos capitanes están de acuerdo en solicitar conjuntamente la revisión de la jugada. | G9: A | H9: Las decisiones sobre hechos sucedidos durante el encuentro, incluido dar por válido un gol, son irrevocables. | I9: Regla 5.2 | J9: 1
A10: RJ5-009 | B10: situacion | C10: Tras reanudar el juego con un saque de esquina, el árbitro se da cuenta de que debía haber concedido un saque de meta. El árbitro... | D10: No puede cambiar la decisión sobre la reanudación. | E10: Puede cambiarla mientras el balón no salga del área. | F10: Puede cambiarla durante el primer minuto tras la reanudación. | G10: A | H10: Una vez reanudado el juego, el árbitro no podrá cambiar la decisión sobre la forma de reanudarlo, aunque se dé cuenta de que era incorrecta. | I10: Regla 5.2 | J10: 2
A11: RJ5-010 | B11: situacion | C11: Al finalizar el primer tiempo, el árbitro abandona el terreno de juego dirigiéndose al área de revisión. Antes de que termine ese periodo, ¿puede modificar una decisión relativa a un incidente sucedido durante el mismo? | D11: Sí, sigue siendo posible modificar una decisión relativa a un incidente sucedido antes de que finalizase ese tiempo. | E11: No, en cuanto el árbitro abandona el terreno de juego pierde la posibilidad de modificar decisiones de ese periodo. | F11: Sí, si la modificación afecta a la validez de un gol y no a cualquier otro tipo de incidente. | G11: A | H11: Si el árbitro abandona el terreno de juego al término de un periodo para dirigirse al área de revisión, aún es posible modificar una decisión relativa a un incidente sucedido antes de que finalizase ese tiempo. | I11: Regla 5.2 | J11: 3
A12: RJ5-011 | B12: situacion | C12: El cuarto árbitro advierte una infracción merecedora de amonestación e intenta comunicarla antes de la reanudación, pero el árbitro no la recibe hasta que el juego ya se ha reanudado. El árbitro... | D12: Puede amonestar, sin modificar la reanudación. | E12: Puede amonestar y debe repetir la reanudación. | F12: No puede amonestar, al haberse reanudado el juego. | G12: A | H12: Regla 5.2: una vez reanudado el juego, «solo podrá imponerse una sanción disciplinaria en el caso de que otro miembro del equipo arbitral haya detectado una infracción y haya intentado comunicarla antes de la reanudación; a tales efectos, la sanción no conllevará la reanudación del juego vinculada con ella». | I12: Regla 5.2 | J12: 3
A13: RJ5-012 | B13: situacion | C13: Si el árbitro no estuviera en condiciones de seguir dirigiendo el partido, este: | D13: Se detendrá de inmediato y no podrá continuar hasta que se incorpore un nuevo árbitro principal. | E13: Podrá continuar, dirigido por el árbitro asistente más antiguo, hasta que finalice esa parte del partido. | F13: Podrá continuar, bajo la supervisión del resto del equipo arbitral, hasta que el balón deje de estar en juego. | G13: C | H13: Si el árbitro no está en condiciones de seguir dirigiendo el partido, podrá continuar bajo la supervisión de los demás miembros del equipo arbitral hasta que el balón deje de estar en juego. | I13: Regla 5.2 | J13: 2
... A82: RJ12-001 | B82: situacion | C82: Se cometen dos infracciones al mismo tiempo. El árbitro sancionará la más grave en función de: | D82: La sanción, la reanudación, la gravedad física y las repercusiones tácticas. | E82: El orden en que se cometieron y el equipo que tenía la posesión. | F82: La zona del terreno de juego y la posición del balón en ese momento. | G82: A | H82: Regla 5.3: «cuando se cometa más de una infracción al mismo tiempo, castigará la infracción más grave en función de la sanción, la reanudación, la gravedad física y las repercusiones tácticas». | I82: Regla 5.3 | J82: 4

Sheet Regla 6
A1: ID | B1: Tipo | C1: Enunciado | D1: Opción A | E1: Opción B | F1: Opción C | G1: Correcta | H1: Explicación | I1: Referencia | J1: Dificultad
A2: RJ6-001 | B2: situacion | C2: Se ha marcado un gol, pero el balón parece seguir en juego. ¿Qué señal debe hacer el árbitro asistente? | D2: Correr rápidamente 25-30 m por la banda hacia la línea central. | E2: Correr rápidamente 25-30 m por la banda hacia la línea central, con una señal discreta. | F2: Levantar primero el banderín y después correr 25-30 m por la banda hacia la línea central. | G2: C | H2: Directrices prácticas (pág. 117): si se ha marcado gol pero el balón parece hallarse aún en juego, el asistente deberá primeramente levantar el banderín para atraer la atención del árbitro y luego correr 25-30 m hacia la línea de medio campo. | I2: Regla 6 | J2: 3
A3: RJ6-002 | B3: directa | C3: Según la Regla 6, el árbitro asistente de reserva: | D3: Reemplazará a un asistente, al cuarto árbitro o a un asistente adicional que no pueda continuar, y ayudará al árbitro como el resto del equipo arbitral. | E3: Reemplazará a un asistente o al cuarto árbitro que no pueda continuar, sin ayudar al árbitro en ninguna otra función durante el partido. | F3: Ayudará al árbitro en el control del área técnica, sin poder reemplazar a ningún otro miembro del equipo arbitral durante el partido. | G3: A | H3: El asistente de reserva puede sustituir a cualquier miembro del equipo arbitral que no pueda continuar (asistente, 4º árbitro o asistente adicional) y colabora con el árbitro principal igual que el resto del equipo arbitral. | I3: Regla 6 | J3: 2
A4: RJ6-005 | B4: directa | C4: ¿Cuáles son los miembros del equipo arbitral en el terreno de juego? | D4: El árbitro principal, los árbitros asistentes, el cuarto árbitro, los árbitros asistentes adicionales y el árbitro asistente de reserva. | E4: El árbitro principal, los árbitros asistentes, el cuarto árbitro, los árbitros asistentes adicionales y el VAR. | F4: El árbitro principal, los árbitros asistentes y el árbitro asistente de reserva, quedando el resto fuera de esta categoría. | G4: A | H4: Son miembros del equipo arbitral en el terreno de juego el árbitro principal, los árbitros asistentes, el cuarto árbitro, los árbitros asistentes adicionales y el árbitro asistente de reserva. | I4: Regla 6 | J4: 1
A5: RJ6-006 | B5: directa | C5: ¿A qué categoría pertenecen el VAR y el AVAR dentro del equipo arbitral? | D5: Son los miembros del equipo arbitral de vídeo, dentro del equipo arbitral. | E5: Son miembros del equipo arbitral en el terreno de juego, igual que los árbitros asistentes. | F5: No forman parte del equipo arbitral, sino de un servicio técnico externo contratado por la competición. | G5: A | H5: El VAR y el AVAR son los miembros del equipo arbitral de vídeo, y ayudan al árbitro conforme a las Reglas de Juego y al Protocolo del VAR. | I5: Regla 6 | J5: 1
A6: RJ6-007 | B6: situacion | C6: Un árbitro asistente incurre en una interferencia indebida o en una conducta incorrecta durante el partido. El árbitro... | D6: Prescinde de sus servicios e informa a las autoridades competentes. | E6: Le advierte verbalmente y permite que continúe en el partido. | F6: Suspende el partido e informa a las autoridades competentes. | G6: A | H6: El resto de miembros del equipo arbitral actuará bajo la dirección del árbitro principal; en caso de interferencia indebida o conducta incorrecta, el árbitro prescindirá de sus servicios e informará a las autoridades competentes. | I6: Regla 6 | J6: 2
A7: RJ6-008 | B7: situacion | C7: Un árbitro asistente tiene un mejor ángulo de visión que el árbitro principal sobre una infracción. ¿Qué debe hacer? | D7: Ayudar al árbitro principal a determinar las faltas e infracciones. | E7: Detener el juego con su banderín sin comunicárselo al árbitro principal. | F7: Abstenerse de intervenir, ya que la decisión final corresponde al árbitro principal. | G7: A | H7: Los otros miembros del equipo arbitral en el terreno de juego ayudarán al árbitro principal a determinar las faltas e infracciones cuando tengan un mejor ángulo de visión. | I7: Regla 6 | J7: 2
A8: RJ6-009 | B8: situacion | C8: Un miembro del equipo arbitral aprecia una conducta incorrecta grave que no han visto ni el árbitro ni el resto del equipo arbitral. ¿Qué debe hacer? | D8: Incluirla en un informe al final de la temporada sobre las incidencias del club. | E8: Informar a las autoridades competentes y dar parte de ello al resto del equipo arbitral. | F8: Nada, porque no fue apreciada ni sancionada en el terreno de juego durante el partido. | G8: B | H8: Deberán informar a las autoridades competentes sobre cualquier conducta incorrecta grave u otros incidentes no apreciados por el árbitro ni por el resto del equipo arbitral, y dar parte de ello a los demás miembros. | I8: Regla 6 | J8: 2
A9: RJ6-010 | B9: situacion | C9: Además de ayudar a determinar las infracciones, los miembros del equipo arbitral en el terreno de juego ayudan al árbitro a: | D9: Inspeccionar el terreno, los balones y el equipamiento, y registrar el tiempo, los goles y la conducta incorrecta. | E9: Registrar el tiempo, los goles y la conducta incorrecta, sin intervenir en la inspección del equipamiento. | F9: Inspeccionar el terreno, los balones y el equipamiento, y supervisar el acceso de los medios de comunicación. | G9: A | H9: Los miembros del equipo arbitral en el terreno de juego ayudan al árbitro a inspeccionar el terreno de juego, los balones y el equipamiento de los jugadores, y a mantener registros de tiempo, goles y conducta incorrecta. | I9: Regla 6 | J9: 2
A10: RJ6-011 | B10: situacion | C10: Para el caso de que el árbitro no pueda continuar, ¿qué deberá dejar claro el reglamento de la competición? | D10: Si asumirá sus funciones el cuarto árbitro, el primer asistente o el primer asistente adicional. | E10: Si asumirá sus funciones el delegado de campo o el capitán del equipo local hasta el final. | F10: Si el partido se suspenderá o se dará por finalizado con el resultado que hubiera en ese momento. | G10: A | H10: El reglamento de la competición deberá estipular claramente quién sustituirá a un miembro del equipo arbitral que no pueda continuar su labor, dejando claro si asumirá las funciones del árbitro el cuarto árbitro, el primer asistente o el primer asistente adicional. | I10: Regla 6 | J10: 3
A11: RJ6-012 | B11: directa | C11: ¿Cuál de las siguientes NO es una tarea propia de los árbitros asistentes según la Regla 6? | D11: Indicar si el balón ha salido completamente del terreno de juego y a qué equipo corresponde el saque. | E11: Mostrar directamente tarjetas amarillas o rojas a los jugadores sin intervención del árbitro principal. | F11: Indicar si un jugador en posición de fuera de juego debe ser sancionado. | G11: B | H11: Los árbitros asistentes indican si el balón ha salido del terreno de juego y a qué equipo corresponde el saque, si un jugador en fuera de juego debe ser sancionado o si se solicita una sustitución, entre otras tareas; no tienen la facultad de mostrar tarjetas directamente. | I11: Regla 6.1 | J11: 2
A12: RJ6-013 | B12: situacion | C12: En el lanzamiento de un tiro penal, el árbitro asistente indicará: | D12: Si el guardameta se separa de la línea de meta antes del lanzamiento y si el balón cruza la línea de meta. | E12: Si el ejecutor toca el balón dos veces antes de que lo toque otro jugador y si el balón cruza la línea de meta. | F12: Si algún jugador entra en el área antes del lanzamiento y si el balón cruza completamente la línea de meta. | G12: A | H12: En el lanzamiento de un tiro penal, el árbitro asistente indicará si el guardameta se separa de la línea de meta antes del lanzamiento y si el balón cruza la línea de meta. | I12: Regla 6.1 | J12: 2
A13: RJ6-014 | B13: situacion | C13: En un partido se han designado árbitros asistentes adicionales. ¿Dónde debe situarse el árbitro asistente durante la ejecución de un tiro penal? | D13: A la altura del punto de penal, sobre la línea de banda. | E13: Detrás del banderín de esquina más cercano a la portería donde se ejecuta el penal. | F13: En la intersección de la línea de meta con el área de meta, junto al poste. | G13: A | H13: Si se hubieran designado árbitros asistentes adicionales, el árbitro asistente deberá situarse a la altura del punto de penal. | I13: Regla 6.1 | J13: 3
... A49: RJ6-060 | B49: situacion | C49: En una jugada de fuera de juego dudosa, un árbitro asistente retrasa levantar el banderín para no interrumpir un ataque claro. ¿Es correcto? | D49: Sí, forma parte del criterio que deben aplicar los árbitros asistentes. | E49: No, debe señalar el fuera de juego de inmediato en cuanto lo aprecie. | F49: No, salvo que el árbitro le haya autorizado antes a retrasar la señal. | G49: A | H49: Los árbitros asistentes deben aplicar el criterio de retrasar la señal de fuera de juego en situaciones de ataque claro que lo justifiquen, como parte de su forma de señalizar correctamente. | I49: Regla 6 | J49: 3

Sheet Regla 7
A1: ID | B1: Tipo | C1: Enunciado | D1: Opción A | E1: Opción B | F1: Opción C | G1: Correcta | H1: Explicación | I1: Referencia | J1: Dificultad
A2: RJ7-001 | B2: situacion | C2: El árbitro añade 3 minutos de tiempo añadido; en el minuto 92:50 se produce un penal a favor de un equipo. ¿Qué decisión toma el árbitro? | D2: Decreta el final del encuentro, ya que el lanzamiento sería fuera de tiempo. | E2: Prolonga el tiempo necesario hasta que se ejecute el penal. | F2: Puede lanzarse por haberse producido antes del minuto 93:00; si hubiera sido después, decretaría el final. | G2: B | H2: Cuando se concede un penal antes de finalizar el tiempo (incluido el añadido), se prolonga el partido el tiempo necesario hasta que se ejecute y resuelva el lanzamiento. Esto incluye la repetición del lanzamiento si procede (por ejemplo, tras un rechace con infracción). | I2: Regla 7 | J2: 3
A3: RJ7-005 | B3: directa | C3: ¿En qué condiciones pueden reducirse los dos periodos de 45 minutos? | D3: Por acuerdo entre el árbitro y los dos equipos antes del comienzo del partido, si lo permite el reglamento de la competición. | E3: Por decisión del árbitro, comunicándolo a ambos equipos antes del inicio del encuentro. | F3: Por acuerdo entre los dos equipos antes del comienzo del partido, sin que sea necesaria la conformidad del árbitro. | G3: A | H3: Los periodos solo pueden reducirse por acuerdo entre el árbitro y los dos equipos antes del comienzo del partido, siempre que esté permitido por el reglamento de la competición. | I3: Regla 7.1 | J3: 2
A4: RJ7-006 | B4: directa | C4: ¿Cuál es la duración máxima de la pausa del descanso de medio tiempo a la que tienen derecho los jugadores? | D4: No superior a 15 minutos. | E4: No superior a 10 minutos. | F4: No superior a 20 minutos. | G4: A | H4: Los jugadores tendrán derecho a una pausa en el descanso de medio tiempo no superior a 15 minutos. | I4: Regla 7.2 | J4: 1
A5: RJ7-007 | B5: directa | C5: ¿Quién puede modificar la duración de la pausa de medio tiempo estipulada por el reglamento de la competición? | D5: Solo con el permiso del árbitro, aunque el reglamento de la competición fije otra duración. | E5: No podrá modificarse una vez fijada por el reglamento de la competición. | F5: Podrá modificarse por acuerdo entre los dos capitanes antes del inicio del partido. | G5: A | H5: El reglamento de la competición deberá estipular claramente la duración de la pausa de medio tiempo, la cual solamente podrá modificarse con el permiso del árbitro. | I5: Regla 7.2 | J5: 2
A6: RJ7-008 | B6: situacion | C6: Tras el primer periodo del tiempo suplementario (prórroga), ¿qué tipo de pausa se permite? | D6: Una pausa idéntica a la del descanso de medio tiempo, de hasta 15 minutos de duración. | E6: Una pausa breve para beber no superior a un minuto. | F6: No se permite ningún tipo de pausa adicional tras el primer periodo de la prórroga. | G6: B | H6: También se permite una pausa breve para beber, no superior a un minuto, tras el primer periodo del tiempo suplementario. | I6: Regla 7.2 | J6: 2
A7: RJ7-009 | B7: directa | C7: ¿Por cuál de los siguientes motivos NO podrá el árbitro prolongar un periodo para recuperar el tiempo perdido? | D7: Por sustituciones realizadas durante ese periodo, sin que sea necesario acreditar el tiempo exacto empleado. | E7: Por la atención o retirada de jugadores lesionados, con independencia de la gravedad de la lesión sufrida. | F7: Por una protesta verbal de un capitán ante una decisión arbitral que el árbitro considera ajustada a las reglas. | G7: C | H7: El árbitro podrá prolongar el periodo por motivos como sustituciones, atención a lesionados, pérdida deliberada de tiempo, sanciones disciplinarias, pausas médicas, retrasos del VAR, celebraciones de goles u otros retrasos significativos; una simple protesta verbal sin más consecuencia no figura entre esos motivos. | I7: Regla 7.3 | J7: 2
A8: RJ7-010 | B8: directa | C8: ¿Cuál es la duración máxima de las pausas de rehidratación que pueden autorizarse conforme al reglamento de la competición? | D8: No superior a un minuto. | E8: No superior a 30 segundos. | F8: Entre 90 segundos y tres minutos. | G8: A | H8: Entre los motivos para recuperar el tiempo perdido se incluyen las pausas de rehidratación, que no serán superiores a un minuto. | I8: Regla 7.3 | J8: 2
A9: RJ7-011 | B9: situacion | C9: Las pausas de refresco que puede contemplar el reglamento de la competición tendrán una duración de: | D9: Entre 90 segundos y 3 minutos. | E9: Entre 2 y 5 minutos como máximo. | F9: No superior a un minuto. | G9: A | H9: Entre los motivos para recuperar el tiempo perdido se incluyen las pausas de refresco, de entre 90 segundos y tres minutos. | I9: Regla 7.3 | J9: 2
A10: RJ7-012 | B10: situacion | C10: Durante un periodo se producen sustituciones, sanciones disciplinarias que requieren tiempo, celebraciones prolongadas de goles, revisiones o chequeos del VAR, pérdida deliberada de tiempo, o un retraso significativo por la interferencia de un agente externo (por ejemplo, un espectador que invade el campo). ¿Puede el árbitro prolongar el periodo para recuperar el tiempo perdido por estos motivos? | D10: Sí, todos son motivos válidos para prolongar el periodo y recuperar el tiempo perdido. | E10: Solo por las sustituciones; el resto de motivos no justifica prolongar el periodo. | F10: No, el tiempo perdido solo puede compensarse por acuerdo previo de ambos equipos. | G10: A | H10: El árbitro puede prolongar el periodo para recuperar el tiempo perdido por sustituciones, atención de lesiones, sanciones disciplinarias, pausas, celebraciones de goles, retrasos por chequeos y revisiones del VAR, pérdida deliberada de tiempo y, en general, cualquier retraso significativo al reanudarse el juego (incluida la interferencia de agentes externos). | I10: Regla 7.3 | J10: 3
A11: RJ7-013 | B11: directa | C11: ¿Quién indica el tiempo mínimo que deberá añadirse al final de cada periodo? | D11: El primer árbitro asistente, mediante comunicación directa al marcador electrónico del estadio. | E11: El árbitro asistente de vídeo, de forma vinculante para el árbitro principal. | F11: El cuarto árbitro, si bien la decisión final corresponde al árbitro. | G11: C | H11: El cuarto árbitro indicará el tiempo mínimo que deberá añadirse, si bien el árbitro tomará la decisión final al respecto. | I11: Regla 7.3 | J11: 2
A12: RJ7-014 | B12: directa | C12: ¿Puede el árbitro reducir el tiempo añadido indicado por el cuarto árbitro? | D12: No, el árbitro podrá aumentar el tiempo añadido, pero no reducirlo. | E12: Sí, el árbitro puede tanto aumentar como reducir el tiempo indicado por el cuarto árbitro. | F12: Sí, si ambos equipos están de acuerdo en que el tiempo indicado es excesivo. | G12: A | H12: El cuarto árbitro indicará el tiempo mínimo a añadir, pero el árbitro tomará la decisión final y podrá aumentar el tiempo añadido, aunque no reducirlo. | I12: Regla 7.3 | J12: 2
A13: RJ7-015 | B13: situacion | C13: En la primera parte, el árbitro añadió por error menos tiempo del debido. ¿Puede compensarlo alargando la segunda parte? | D13: No, no puede compensar el error cambiando la duración de la segunda parte. | E13: Sí, debe compensarlo añadiendo ese tiempo al final de la segunda parte. | F13: Sí, si el tiempo que añade a la segunda parte no supera los cinco minutos. | G13: A | H13: El árbitro no podrá compensar un error de cronometraje del primer periodo cambiando la duración del segundo periodo. | I13: Regla 7.3 | J13: 2
... A39: RJ7-050 | B39: situacion | C39: Tras añadir en la primera parte el tiempo perdido por una lesión, el árbitro quiere recortar ese mismo tiempo en la segunda parte para que el partido no dure más de lo previsto. ¿Puede hacerlo? | D39: No, no puede reducir una parte para compensar la otra. | E39: Sí, si la suma de las dos partes es la duración total. | F39: Sí, si ambos equipos lo aceptan antes de la segunda parte. | G39: A | H39: El árbitro no podrá compensar un error o un ajuste de cronometraje de un periodo cambiando la duración de otro; cada periodo se gestiona de forma independiente. | I39: Regla 7 | J39: 3

Sheet Regla 8
A1: ID | B1: Tipo | C1: Enunciado | D1: Opción A | E1: Opción B | F1: Opción C | G1: Correcta | H1: Explicación | I1: Referencia | J1: Dificultad
A2: RJ8-001 | B2: situacion | C2: El árbitro concede un balón a tierra al guardameta dentro de su propia área penal. ¿Deben el resto de jugadores abandonar el área penal? | D2: No es obligatorio abandonar el área; basta con que todos los jugadores, de ambos equipos, guarden una distancia mínima de 4 metros con respecto al balón hasta que esté en juego. | E2: Sí; todos los jugadores de ambos equipos deben abandonar el área penal, pudiendo permanecer dentro solo el guardameta. | F2: Los adversarios deben abandonar el área; los compañeros del guardameta pueden permanecer dentro, guardando una distancia mínima de 4 metros con respecto al balón. | G2: A | H2: El resto de jugadores, de ambos equipos, deberán mantener una distancia mínima de 4 m (4,5 yd) con respecto al balón hasta que esté en juego; no existe obligación de abandonar el área penal. | I2: Regla 8 | J2: 3
A3: RJ8-002 | B3: directa | C3: ¿Qué condición debe darse para que sea válido un gol tras un balón a tierra? | D3: Que el balón haya tocado como mínimo a dos jugadores. | E3: Que el balón haya tocado a dos jugadores del mismo equipo. | F3: Que el balón haya tocado a dos jugadores, uno de cada equipo. | G3: A | H3: Si tras un balón a tierra el balón entra en la portería sin haber tocado como mínimo a dos jugadores, no sube el gol; la regla no exige que esos dos jugadores pertenezcan a equipos distintos. | I3: Regla 8 | J3: 1
A4: RJ8-003 | B4: situacion | C4: El árbitro detiene el juego por una causa no prevista en otra regla (por ejemplo, un objeto lanzado desde la grada, o una lesión), sin que ningún equipo haya cometido infracción. ¿Cómo reanuda el juego? | D4: Con un balón a tierra en el lugar donde se encontraba el balón cuando se detuvo el juego. | E4: Con un tiro libre indirecto a favor del equipo que tuviera la posesión en ese momento. | F4: Con un saque de banda a favor del equipo más cercano al lugar de la detención. | G4: A | H4: Cuando el juego se detiene sin que se haya cometido ninguna infracción (por cualquier causa no prevista expresamente, como una lesión o la interferencia de un objeto), se reanuda con un balón a tierra en el lugar donde se encontraba el balón. | I4: Regla 8 | J4: 4
A5: RJ8-004 | B5: situacion | C5: El equipo que realiza el saque inicial pasa el balón con el pie, de forma deliberada, hacia su guardameta, que lo coge con las manos dentro de su área. ¿Qué decide el árbitro? | D5: Concede un tiro libre indirecto al equipo adversario. | E5: Permite que continúe el juego, porque el balón procede de un saque inicial. | F5: Concede un tiro libre directo al equipo adversario. | G5: A | H5: La excepción para que el guardameta toque con las manos un balón recibido directamente de un saque solo recoge el saque de banda. Un pase deliberado con el pie de un compañero, aunque sea desde el saque inicial, se castiga con libre indirecto. | I5: Regla 8 | J5: 3
A6: RJ8-005 | B6: situacion | C6: En el saque inicial, ¿pueden los adversarios del equipo que saca situarse dentro del círculo central? | D6: No, deben permanecer fuera del círculo central (al menos a 9,15 m del balón) hasta que el balón esté en juego. | E6: Sí, si no llegan a tocar el balón antes de que este esté en juego. | F6: Sí, el capitán rival puede permanecer dentro del círculo, y el resto de sus compañeros fuera. | G6: A | H6: En el saque inicial, todos los jugadores del equipo que no saca deben permanecer fuera del círculo central hasta que el balón esté en juego. | I6: Regla 8 | J6: 2
A7: RJ8-007 | B7: situacion | C7: El árbitro detiene el juego por un motivo no contemplado en las Reglas de Juego. ¿Cómo se reanuda el juego? | D7: Con un balón a tierra. | E7: Con un saque de banda a favor del equipo más próximo. | F7: Con un tiro libre indirecto a favor del equipo que tenía el balón. | G7: A | H7: Cuando el árbitro detenga el juego por un motivo no contemplado en las Reglas de Juego, este se reanudará con un balón a tierra. | I7: Regla 8 | J7: 1
A8: RJ8-008 | B8: situacion | C8: Se comete una infracción mientras el balón no está en juego. ¿Afecta a la forma en que se reanudará el juego? | D8: No. | E8: Sí, la reanudación se concede al equipo perjudicado. | F8: Sí, si la comete un jugador y no un suplente. | G8: A | H8: Las infracciones cometidas cuando el balón no esté en juego no afectarán a la manera en que este se reanude. | I8: Regla 8.1 | J8: 2
A9: RJ8-012 | B9: situacion | C9: En el saque inicial, ¿dónde deben situarse los jugadores, excepto el ejecutor, y a qué distancia del balón deben encontrarse los adversarios del equipo que saca? | D9: Todos, excepto el ejecutor, en su propia mitad del terreno de juego; los adversarios, además, a un mínimo de 9,15 m del balón hasta que entre en juego. | E9: Todos, excepto el ejecutor, en su propia mitad del terreno de juego; los adversarios, además, a un mínimo de 4 m del balón hasta que entre en juego. | F9: Los compañeros del ejecutor pueden situarse en cualquier mitad del terreno de juego; los adversarios, en su propia mitad y a un mínimo de 9,15 m del balón. | G9: A | H9: En el saque inicial, todos los jugadores, excepto el que ejecute el saque, deberán encontrarse en su propia mitad del terreno de juego, y los adversarios del equipo que efectúe el saque, como mínimo a 9,15 m (10 yd) del balón hasta que entre en juego. | I9: Regla 8.1 | J9: 2
A10: RJ8-013 | B10: directa | C10: ¿A qué distancia mínima del balón deben encontrarse los adversarios del equipo que efectúa el saque inicial? | D10: 9,15 metros (10 yardas), hasta que el balón entre en juego. | E10: 4 metros (4,5 yardas), igual que en el caso de un balón a tierra. | F10: 5 metros, distancia general aplicable a cualquier reanudación del juego. | G10: A | H10: Los adversarios del equipo que efectúe el saque deberán encontrarse como mínimo a 9,15 m (10 yd) del balón hasta que entre en juego. | I10: Regla 8.1 | J10: 1
A11: RJ8-014 | B11: directa | C11: ¿Puede el balón golpearse con el pie en el saque inicial antes de que el árbitro dé la señal? | D11: No, el balón se colocará en el punto central y no se podrá golpear con el pie hasta que el árbitro lo indique. | E11: Sí, si el equipo que ejecute el saque avisa previamente al árbitro de su intención de sacar. | F11: Sí, el balón puede golpearse en cuanto esté correctamente colocado en el punto central, sin esperar señal. | G11: A | H11: En el saque inicial, el balón se colocará en el punto central y no se podrá golpear con el pie hasta que el árbitro así lo indique. | I11: Regla 8.1 | J11: 1
A12: RJ8-016 | B12: situacion | C12: En un saque inicial, el balón entra directamente en la meta del equipo que ejecuta el saque, sin haber sido tocado por ningún otro jugador. ¿Qué decisión debe tomar el árbitro? | D12: Ordenará la repetición del saque inicial, sin conceder ninguna reanudación a favor del adversario. | E12: Concederá un gol válido al equipo adversario, al haber entrado el balón en la portería. | F12: Concederá un saque de esquina al equipo adversario. | G12: C | H12: Será posible marcar un gol directo al equipo adversario desde el saque inicial; si el balón entrara directamente en la meta del lanzador, se concederá saque de esquina al adversario. | I12: Regla 8.1 | J12: 2
A13: RJ8-017 | B13: situacion | C13: El jugador que ejecuta el saque inicial toca el balón por segunda vez de forma voluntaria con el pie, antes de que lo haya tocado otro jugador. ¿Qué decisión toma el árbitro? | D13: Concederá un tiro libre indirecto a favor del equipo adversario. | E13: Ordenará la repetición del saque inicial, sin sanción adicional para el equipo infractor. | F13: Concederá un tiro libre directo a favor del equipo adversario. | G13: A | H13: En caso de que el jugador que ejecute el saque inicial toque el balón por segunda vez antes de que lo toque otro jugador, se concederá un tiro libre indirecto, o bien un libre directo si cometiese una infracción por mano. | I13: Regla 8.1 | J13: 2
... A40: RJ8-058 | B40: situacion | C40: En el saque inicial, un adversario se sitúa dentro del círculo central sin que el árbitro lo advierta e intercepta el balón en el momento del golpeo. El árbitro... | D40: Ordena repetir el saque inicial. | E40: Deja que el juego continúe. | F40: Concede un tiro libre indirecto. | G40: A | H40: Todos los jugadores del equipo que no ejecuta el saque inicial deben permanecer a una distancia mínima de 9,15 m del balón hasta que este esté en juego; su incumplimiento obliga a repetir el saque. | I40: Regla 8 | J40: 3

Sheet Regla 9
A1: ID | B1: Tipo | C1: Enunciado | D1: Opción A | E1: Opción B | F1: Opción C | G1: Correcta | H1: Explicación | I1: Referencia | J1: Dificultad
A2: RJ9-001 | B2: situacion | C2: Durante el partido, un segundo balón entra en el terreno de juego sin interferir en el juego. El árbitro... | D2: Deja que el juego continúe; si llega a interferir, lo detiene y reanuda con un balón a tierra. | E2: Detiene el juego para retirarlo, aunque no interfiera, y reanuda con un balón a tierra. | F2: Detiene el juego para retirarlo, aunque no interfiera, y reanuda con un saque de banda. | G2: A | H2: El criterio general es dejar continuar el juego si el balón sobrante no interfiere; si interfiere, se detiene y reanuda con balón a tierra, salvo las excepciones relativas a un gol que ya iba a producirse. | I2: Regla 9 | J2: 4
A3: RJ9-002 | B3: situacion | C3: Un atacante dispara a portería desde fuera del área; el balón golpea al árbitro, situado dentro del área penal, y sale por la línea de meta. ¿Cómo se reanuda el juego? | D3: Con un saque de meta. | E3: Con un balón a tierra a favor del equipo atacante. | F3: Con un balón a tierra al guardameta del equipo defensor. | G3: A | H3: Cuando el balón sale por línea de meta tras tocar al árbitro (agente neutro) sin haber entrado en la portería, se reanuda con saque de meta, como en cualquier salida por esa línea procedente de un atacante. | I3: Regla 9 | J3: 3
A4: RJ9-003 | B4: situacion | C4: El guardameta lanza el balón lejos de su portería para pedir asistencia médica; el árbitro detiene el juego justo cuando el balón iba a ser recogido con claridad por un jugador del equipo contrario. ¿Cómo reanuda el árbitro el juego? | D4: Con balón a tierra a favor del equipo del guardameta, en el lugar donde estaba el balón al detenerse el juego. | E4: Con balón a tierra a favor del portero, dentro de su propia área. | F4: Con balón a tierra a favor del equipo contrario, en el lugar donde estaba el balón al detenerse el juego. | G4: C | H4: Cuando se detiene el juego por una causa ajena al desarrollo normal (petición de asistencia) y el balón iba a ser recogido claramente por el equipo contrario, el balón a tierra se concede a ese equipo en el lugar donde estaba el balón. | I4: Regla 9 | J4: 4
A5: RJ9-004 | B5: situacion | C5: El balón rebota en un poste y vuelve al terreno de juego sin haber atravesado la línea de meta. ¿Sigue el balón en juego? | D5: Sí. | E5: No, el contacto con la portería lo deja fuera de juego. | F5: Solo si después lo toca el guardameta. | G5: A | H5: El balón permanece en juego tras rebotar en los postes o el travesaño, siempre que no haya cruzado completamente la línea correspondiente ni el árbitro haya detenido el juego. | I5: Regla 9 | J5: 3
A6: RJ9-005 | B6: situacion | C6: Un espectador invade el terreno de juego, toca el balón e interfiere en el juego. ¿Cómo se reanuda el juego? | D6: Con un balón a tierra. | E6: Con un saque de banda, de meta o de esquina, según por dónde salga. | F6: Con un tiro libre indirecto a favor del equipo perjudicado. | G6: A | H6: Cuando un agente externo (incluido un espectador que invade el terreno) toca el balón interfiriendo el juego, se reanuda con balón a tierra en el lugar donde se produjo el contacto. | I6: Regla 9 | J6: 4
A7: RJ9-007 | B7: situacion | C7: Además de salir del terreno de juego, ¿en qué otro caso general el balón no estará en juego? | D7: Cuando el juego haya sido detenido por el árbitro. | E7: Cuando el balón toque a cualquier miembro del equipo arbitral. | F7: Cuando el balón rebote en el poste o el travesaño y permanezca en el terreno de juego. | G7: A | H7: El balón no estará en juego cuando el juego haya sido detenido por el árbitro. | I7: Regla 9.1 | J7: 1
A8: RJ9-008 | B8: situacion | C8: El balón toca a un árbitro asistente y permanece en el terreno de juego. ¿En cuál de estos casos deja de estar en juego? | D8: Si a raíz del contacto un equipo inicia un ataque prometedor o cambia el equipo en posesión del balón. | E8: Solo si a raíz del contacto un equipo inicia un ataque prometedor, pero no si cambia la posesión. | F8: Solo si a raíz del contacto cambia el equipo en posesión del balón, pero no si se inicia un ataque. | G8: A | H8: El balón deja de estar en juego cuando, tras tocar a un miembro del equipo arbitral, se inicia un ataque prometedor o cambia el equipo en posesión del balón; son dos de las excepciones previstas junto con la entrada directa en la portería. | I8: Regla 9.1 | J8: 3
A9: RJ9-009 | B9: situacion | C9: El balón toca al árbitro principal, permanece en el terreno de juego y entra directamente en la portería. ¿Qué decisión toma el árbitro? | D9: El balón habrá dejado de estar en juego, por lo que no se concederá el gol y se reanudará con un balón a tierra. | E9: Se concederá el gol, ya que el balón permaneció en el terreno de juego en todo momento tras el contacto. | F9: Se concederá el gol si el contacto con el árbitro fue accidental y no evitable por su parte. | G9: A | H9: El balón no estará en juego cuando toque a un miembro del equipo arbitral, permanezca en el terreno de juego y entre directamente en la portería; el juego se reanudará con un balón a tierra. | I9: Regla 9.1 | J9: 2
A10: RJ9-011 | B10: situacion | C10: El balón deja de estar en juego al tocar a un miembro del equipo arbitral. ¿Cómo se reanuda el juego? | D10: Con un balón a tierra. | E10: Con un tiro libre indirecto a favor del equipo que tenía el balón. | F10: Con un saque de banda a favor del equipo más próximo. | G10: A | H10: En todos los casos en los que el balón no esté en juego por contacto con un miembro del equipo arbitral en las circunstancias previstas, el juego se reanudará con un balón a tierra. | I10: Regla 9.1 | J10: 1
A11: RJ9-012 | B11: situacion | C11: El balón toca a un árbitro asistente y permanece en el terreno de juego, sin que se inicie un ataque prometedor, entre directamente en la portería ni cambie la posesión. ¿Sigue el balón en juego? | D11: Sí. | E11: No, cualquier contacto con el equipo arbitral lo deja fuera de juego. | F11: Solo si el árbitro decide que el juego continúe. | G11: A | H11: El balón estará en juego en el resto de situaciones en las que entre en contacto con un miembro del equipo arbitral, siempre que no se produzcan los supuestos que lo dejan fuera de juego. | I11: Regla 9.2 | J11: 2
A12: RJ9-013 | B12: situacion | C12: Un disparo rebota en un poste y el balón permanece dentro del terreno de juego. ¿Sigue el balón en juego? | D12: No, salvo que el rebote haya sido en el travesaño. | E12: No, el juego se reanuda con un balón a tierra. | F12: Sí, sigue en juego. | G12: C | H12: El balón estará en juego cuando rebote en un poste o un travesaño, o en el banderín de esquina, y permanezca en el terreno de juego. | I12: Regla 9.2 | J12: 1
A13: RJ9-015 | B13: situacion | C13: Un suplente, un jugador lesionado temporalmente fuera del terreno de juego, o un jugador ya sustituido, tocan sin intención de interferir un balón que está claramente a punto de salir del campo. ¿Cómo se sanciona en los tres casos? | D13: En los tres casos igual: tiro libre indirecto a favor del equipo contrario, sin sanción disciplinaria. | E13: Solo el suplente se sanciona con tiro libre indirecto; a los otros dos no se les sanciona. | F13: El suplente y el sustituido se sancionan con tiro libre indirecto; al lesionado no se le sanciona. | G13: A | H13: En los tres casos (suplente, jugador lesionado fuera del terreno, jugador sustituido) se aplica la misma sanción: tiro libre indirecto a favor del equipo contrario, sin sanción disciplinaria, al no existir intención de interferir de forma antirreglamentaria. | I13: Regla 9.2 | J13: 3
... A31: RJ9-038 | B31: situacion | C31: Con el juego detenido por una lesión, el viento empuja el balón, que estaba junto a la línea de meta, hasta que la cruza por completo. ¿Se concede saque de meta o de esquina? | D31: No, el balón no estaba en juego; se reanuda según el motivo de la detención. | E31: Sí, se concede saque de meta o de esquina según quién lo tocó por última vez. | F31: Sí, se concede un saque de esquina, sea cual sea el motivo de la detención. | G31: A | H31: Una vez que el juego está detenido, el balón no está en juego; su desplazamiento posterior por causas ajenas (como el viento) no genera ninguna reanudación relacionada con haber cruzado una línea, y el juego se reanuda conforme a la causa original de la detención. | I31: Regla 9 | J31: 4

Sheet Regla 10
A1: ID | B1: Tipo | C1: Enunciado | D1: Opción A | E1: Opción B | F1: Opción C | G1: Correcta | H1: Explicación | I1: Referencia | J1: Dificultad
A2: RJ10-003 | B2: situacion | C2: El guardameta lanza el balón con la mano y entra directamente en la portería contraria. ¿Qué decisión toma el árbitro? | D2: Concede un saque de meta. | E2: Concede el gol. | F2: Concede un saque de esquina. | G2: A | H2: Si el guardameta lanza el balón con la mano y este entra en la portería contraria directamente, se concederá saque de meta. | I2: Regla 10.1 | J2: 2
A3: RJ10-004 | B3: situacion | C3: El árbitro señala gol antes de que el balón haya traspasado completamente la línea de meta. ¿Cómo debe reanudarse el juego al advertir el error? | D3: Con un balón a tierra. | E3: Con un saque de meta a favor del equipo defensor. | F3: Manteniendo el gol como válido. | G3: A | H3: Si el árbitro señalara un gol antes de que el balón hubiera traspasado completamente la línea de meta, el juego se reanudará con un balón a tierra. | I3: Regla 10.1 | J3: 2
A4: RJ10-007 | B4: directa | C4: ¿Cuáles son los procedimientos permitidos para determinar un vencedor cuando el reglamento de la competición exige que haya un ganador tras un partido empatado? | D4: La regla de goles marcados fuera de casa, dos periodos de tiempo suplementario de igual duración que no excedan los 15 minutos cada uno, y la tanda de penales. | E4: La regla de goles marcados fuera de casa, dos periodos de tiempo suplementario de igual duración que no excedan los 20 minutos cada uno, y la tanda de penales. | F4: La regla de goles marcados fuera de casa, un periodo de tiempo suplementario de 15 minutos, y la tanda de penales. | G4: A | H4: Se permitirán únicamente los siguientes procedimientos para determinar el vencedor: la regla de goles marcados fuera de casa, dos periodos de tiempo suplementario que no excedan los 15 minutos cada uno, y la tanda de penales. | I4: Regla 10.2 | J4: 2
A5: RJ10-008 | B5: directa | C5: ¿Pueden combinarse varios de los procedimientos previstos para determinar un equipo ganador tras un empate? | D5: Sí, se podrán combinar varios de los procedimientos previstos. | E5: No, el reglamento de la competición debe optar por uno solo de los procedimientos. | F5: Sí, se podrán combinar la regla de goles fuera de casa y la tanda de penales, pero no el tiempo suplementario. | G5: A | H5: Se podrán combinar varios de los procedimientos previstos para determinar el vencedor tras un partido empatado. | I5: Regla 10.2 | J5: 2
A6: RJ10-011 | B6: situacion | C6: Un jugador fue amonestado durante el partido. ¿Se tiene en cuenta esa amonestación en la tanda de penales? | D6: No. | E6: Sí, y una nueva amonestación en la tanda conllevaría su expulsión. | F6: Sí, pero solo a efectos estadísticos en el acta del partido. | G6: A | H6: Las advertencias y amonestaciones impuestas a jugadores y miembros del cuerpo técnico durante el encuentro no se tendrán en consideración en la tanda de penales. | I6: Regla 10.3 | J6: 2
A7: RJ10-012 | B7: directa | C7: ¿Cómo se decide en qué portería se desarrollará la tanda de penales? | D7: Mediante un sorteo con moneda, salvo consideraciones como el estado del terreno o la seguridad. | E7: Se utiliza la portería del segundo tiempo, salvo que el estado del terreno o la seguridad lo impidan. | F7: Elige el equipo que ganó el sorteo inicial, salvo que el estado del terreno o la seguridad lo impidan. | G7: A | H7: El árbitro realizará un sorteo mediante moneda para decidir la portería en la que se desarrollará la tanda, salvo que otras consideraciones como el estado del terreno o la seguridad lo impidan. | I7: Regla 10.3 | J7: 2
A8: RJ10-013 | B8: situacion | C8: Una vez elegida la portería, ¿cómo se decide qué equipo lanza primero en la tanda de penales? | D8: Lanza primero el equipo visitante, salvo acuerdo entre capitanes. | E8: Lanza primero el equipo que marcó el primer gol del partido. | F8: Con un nuevo sorteo; el equipo favorecido elige si lanza primero o segundo. | G8: C | H8: El árbitro realizará un nuevo sorteo mediante moneda, y el equipo que resulte favorecido decidirá si ejecuta el primer o el segundo lanzamiento. | I8: Regla 10.3 | J8: 2
A9: RJ10-014 | B9: directa | C9: ¿Qué jugadores pueden participar en la tanda de penales? | D9: Los que estén en el terreno de juego al final del partido o momentáneamente fuera de él. | E9: Todos los jugadores inscritos en el acta, incluidos los sustituidos durante el partido. | F9: Los once jugadores que comenzaron el partido, con independencia de las sustituciones. | G9: A | H9: Solamente estarán autorizados a participar aquellos jugadores que al final del partido se encuentren en el terreno de juego, o momentáneamente fuera del mismo por lesión, cambios de equipamiento, etc. | I9: Regla 10.3 | J9: 2
A10: RJ10-015 | B10: directa | C10: ¿Quién decide el orden en el que cada equipo ejecutará sus lanzamientos en la tanda de penales? | D10: El árbitro, que fija el orden de lanzamiento en función del sorteo inicial de la tanda de penales. | E10: El equipo que gane el sorteo para elegir portería, que también decide el orden de ambos equipos. | F10: Cada equipo decide su propio orden, sin necesidad de informar de él al árbitro con antelación. | G10: C | H10: Cada uno de los equipos se encargará de decidir el orden en el que ejecutará los lanzamientos, sin que se informe del mismo al árbitro. | I10: Regla 10.3 | J10: 2
A11: RJ10-016 | B11: situacion | C11: Al final del partido, el Equipo A tiene más jugadores en el terreno de juego que el Equipo B. Antes de la tanda de penales: | D11: El Equipo B deberá incorporar jugadores desde el banquillo para igualar al Equipo A. | E11: El Equipo A deberá reducir su número para igualarlo e informar al árbitro de los excluidos. | F11: El árbitro suspenderá el partido, al no haber igualdad numérica entre los dos equipos. | G11: B | H11: Si un equipo tiene más jugadores que su adversario al finalizar el partido, deberá reducir su número para igualarlo, informando al árbitro del nombre y número de los jugadores excluidos. | I11: Regla 10.3 | J11: 2
A12: RJ10-017 | B12: situacion | C12: Un guardameta no se encuentra en condiciones de continuar antes de la tanda de penales y su equipo ya ha utilizado el número máximo de sustituciones. ¿Por quién puede ser reemplazado? | D12: Por un jugador excluido para igualar el número de jugadores con el equipo rival. | E12: Por un miembro del cuerpo técnico inscrito en el acta del partido. | F12: No podrá ser reemplazado, debiendo su equipo afrontar la tanda con un jugador de campo en la portería. | G12: A | H12: Un guardameta que no pueda continuar podrá ser reemplazado por un jugador excluido para igualar el número, o, si el equipo no ha agotado sus sustituciones, por un suplente designado en la lista oficial. | I12: Regla 10.3 | J12: 3
A13: RJ10-018 | B13: situacion | C13: En la tanda de penales, un guardameta que ya ha lanzado no puede continuar y es reemplazado. ¿Puede su sustituto lanzar en esa ronda? | D13: No, no podrá lanzar hasta la siguiente ronda. | E13: Sí, ocupará el turno de lanzamiento del guardameta. | F13: Sí, pero solo el lanzamiento inmediatamente posterior. | G13: A | H13: Si el guardameta hubiera ejecutado ya un lanzamiento, el suplente no podrá ejecutar el tiro hasta la siguiente tanda de penales. | I13: Regla 10.3 | J13: 3
... A52: RJ10-064 | B52: situacion | C52: Durante la tanda de penales, tras marcar un gol, un jugador celebra de forma exaltada dirigiéndose de manera provocadora hacia el banquillo rival, sin llegar a faltar el respeto. ¿Puede el árbitro amonestarlo por esta conducta durante la tanda de penales? | D52: Sí, la autoridad disciplinaria del árbitro se mantiene durante la tanda de penales igual que durante el resto del partido. | E52: No, durante la tanda de penales el árbitro pierde la facultad de amonestar por conductas de celebración. | F52: Sí, pero únicamente puede advertirle verbalmente, sin poder mostrarle la tarjeta amarilla en esta fase. | G52: A | H52: La autoridad disciplinaria del árbitro se mantiene durante toda la tanda de penales, pudiendo amonestar o expulsar por las mismas conductas que durante el resto del partido. | I52: Regla 10 | J52: 3

Sheet Regla 11
A1: ID | B1: Tipo | C1: Enunciado | D1: Opción A | E1: Opción B | F1: Opción C | G1: Correcta | H1: Explicación | I1: Referencia | J1: Dificultad
A2: RJ11-001 | B2: situacion | C2: En la disputa de un balón aéreo, un defensor cae accidentalmente fuera del terreno de juego junto a la portería. Un atacante remata el rechace y otro atacante, situado delante del guardameta, le tapa la visión; el balón entra en la portería. ¿Debe anularse el gol por fuera de juego? | D2: Sí, porque el atacante situado delante del guardameta le tapa la visión desde posición de fuera de juego. | E2: No: el defensor cuenta como situado en la línea de meta y el atacante no está en posición de fuera de juego. | F2: Sí, porque el defensor que está fuera del terreno de juego deja de contar a efectos del fuera de juego. | G2: B | H2: A efectos del fuera de juego, el defensor que sale del terreno de juego se considera situado en la línea de meta o de banda. El atacante situado delante del guardameta no está más cerca de la línea de meta que el balón y los dos últimos adversarios (guardameta y defensor), así que no está en posición de fuera de juego y no puede cometer infracción por interferir: el gol es válido. | I2: Regla 11 | J2: 4
A3: RJ11-002 | B3: situacion | C3: Un jugador en posición de fuera de juego y un compañero que no lo está corren ambos hacia el balón; finalmente juega el balón el compañero que no estaba en posición antirreglamentaria. ¿Qué decisión toma el árbitro? | D3: Interrumpe el juego y concede tiro libre indirecto donde se jugó el balón. | E3: Interrumpe el juego y concede tiro libre indirecto por la posición de fuera de juego del otro jugador. | F3: Deja que el juego continúe, salvo que el jugador en posición de fuera de juego interfiera con un adversario. | G3: C | H3: Estar en posición de fuera de juego no constituye infracción por sí sola; solo se sanciona si el jugador interviene interfiriendo en el juego, en un adversario o obtiene ventaja de esa posición. | I3: Regla 11 | J3: 4
A4: RJ11-003 | B4: situacion | C4: Cuando el guardameta lanza el balón con las manos, ¿qué se tiene en cuenta para determinar el fuera de juego? | D4: El primer punto de contacto al 'jugar' o 'tocar' el balón. | E4: El último punto de contacto en el momento de lanzarlo con la mano. | F4: El primer o último contacto, según cada situación concreta. | G4: B | H4: Cuando el guardameta lanza el balón con la mano, para el fuera de juego se toma en cuenta el último punto de contacto del guardameta con el balón. | I4: Regla 11 | J4: 1
A5: RJ11-004 | B5: situacion | C5: Con el balón por detrás de él, un atacante está a la misma altura que el guardameta, que es el último defensor. ¿Está en posición de fuera de juego? | D5: No, porque está a la altura del último adversario. | E5: Sí. | F5: Solo si el guardameta está fuera de su área. | G5: B | H5: Regla 11 (pág. 59): está en posición de fuera de juego quien está más cerca de la línea de meta contraria que el balón y el penúltimo adversario. Solo se libra quien está a la altura del penúltimo adversario o de los dos últimos. Si el guardameta es el último, el penúltimo está más adelantado. | I5: Regla 11 | J5: 2
A6: RJ11-005 | B6: situacion | C6: Un jugador se encuentra en posición de fuera de juego pero no interviene en el juego de ningún modo, ni interfiere a un adversario ni obtiene ventaja de dicha posición. ¿Debe sancionarse? | D6: No, la posición de fuera de juego no es sancionable por sí sola si no interviene activamente. | E6: Sí, si está en posición de fuera de juego cuando el balón sea jugado por un compañero. | F6: Sí, si se encuentra en el área penal contraria. | G6: A | H6: Estar en posición de fuera de juego no constituye infracción en sí misma; se exige intervención activa (jugar el balón, interferir a un adversario u obtener ventaja) para sancionarla. | I6: Regla 11 | J6: 4
A7: RJ11-008 | B7: situacion | C7: Estar en posición de fuera de juego: | D7: No constituye infracción por sí mismo. | E7: Constituye infracción por sí mismo. | F7: Solo es infracción en el campo contrario. | G7: A | H7: El hecho de estar en posición de fuera de juego no constituye infracción por sí mismo. | I7: Regla 11.1 | J7: 1
A8: RJ11-009 | B8: directa | C8: ¿Qué dos condiciones deben cumplirse para que un jugador se encuentre en posición de fuera de juego? | D8: Que su cabeza, tronco o pierna estén en la mitad de campo contraria y más cerca de la línea de meta rival que el balón y el penúltimo adversario. | E8: Que su cabeza, tronco o pierna estén en cualquier parte del terreno de juego y más cerca de la línea de meta rival que el balón y el penúltimo adversario. | F8: Que su cabeza, tronco, pierna o brazo estén en la mitad de campo contraria y más cerca de la línea de meta rival que el balón y el penúltimo adversario. | G8: A | H8: Un jugador está en posición de fuera de juego cuando su cabeza, tronco o pierna se encuentran en la mitad del campo contraria y más cerca de la línea de meta rival que el balón y el penúltimo adversario. | I8: Regla 11.1 | J8: 2
A9: RJ11-010 | B9: directa | C9: ¿Se tienen en cuenta las manos o los brazos de los jugadores para determinar la posición de fuera de juego? | D9: No, no se tendrán en consideración las manos ni los brazos, tampoco en el caso de los guardametas. | E9: Se tienen en cuenta los brazos, pero no las manos, de los jugadores de campo, excluyendo a los guardametas. | F9: Sí, se tienen en cuenta tanto las manos como los brazos de todos los jugadores, incluidos los guardametas. | G9: A | H9: A la hora de determinar si un jugador está en posición de fuera de juego, no se tendrán en consideración las manos ni los brazos de los jugadores, tampoco en el caso de los guardametas. | I9: Regla 11.1 | J9: 1
A10: RJ11-012 | B10: situacion | C10: Un atacante se encuentra a la misma altura que el penúltimo adversario. ¿Está en posición de fuera de juego? | D10: No. | E10: Sí, si está por delante del balón. | F10: Depende de su distancia a la línea de banda. | G10: A | H10: No estará en fuera de juego aquel jugador que se encuentre a la misma altura que el penúltimo adversario o que los dos últimos adversarios. | I10: Regla 11.1 | J10: 2
A11: RJ11-013 | B11: directa | C11: ¿En qué momento se sanciona a un jugador que se encuentra en posición de fuera de juego? | D11: En el momento en que el jugador toca físicamente el balón, con independencia de cuándo se lo hubiera jugado un compañero. | E11: En el momento en que el balón toca o es jugado por un compañero de equipo, siempre que participe de forma activa en el juego. | F11: En el momento en que el árbitro asistente levanta el banderín, aunque el balón aún no haya sido jugado por ningún compañero. | G11: B | H11: Únicamente se sancionará a un jugador en posición de fuera de juego en el momento en que el balón toca o es jugado por un compañero, si llega a participar en el juego de forma activa. | I11: Regla 11.2 | J11: 2
A12: RJ11-014 | B12: directa | C12: ¿Cuál de las siguientes NO es una de las formas en que un jugador en posición de fuera de juego participa de forma activa en el juego? | D12: Impedir que un adversario juegue el balón, al obstruir claramente su campo visual. | E12: Permanecer estático y alejado del balón, sin intervenir de ninguna manera en la jugada en curso. | F12: Interferir en el juego, al jugar o tocar un balón pasado o tocado por un compañero. | G12: B | H12: Un jugador en posición de fuera de juego participa activamente cuando interfiere en el juego, impide que el adversario juegue el balón o le disputa el balón, entre otras acciones; permanecer estático sin intervenir no constituye participación activa. | I12: Regla 11.2 | J12: 2
A13: RJ11-018 | B13: situacion | C13: Un jugador en posición de fuera de juego recibe el balón de un adversario que lo ha jugado voluntariamente. ¿Ha sacado ventaja de su posición? | D13: No, salvo que el adversario haya realizado una «salvada». | E13: Sí, si estaba claramente adelantado respecto del penúltimo defensor. | F13: Sí, aunque el adversario lo haya jugado de forma voluntaria. | G13: A | H13: Se considerará que un jugador en posición de fuera de juego no ha sacado ventaja cuando reciba el balón de un adversario que lo juega voluntariamente, incluida la mano voluntaria, a menos que se trate de una «salvada». | I13: Regla 11.2 | J13: 3
... A62: RJ11-079 | B62: situacion | C62: Los únicos adversarios por detrás del balón son el guardameta, adelantado unos 10 m, y un defensor que ha salido sin permiso por la línea de meta tras un choque. Con el juego en marcha, un compañero pasa el balón a un atacante situado a 5 m de la línea de meta, que marca. El árbitro... | D62: Anula el gol y concede un tiro libre indirecto por fuera de juego donde el atacante recibió el balón. | E62: Concede el gol, porque el defensor que salió sin permiso no cuenta para valorar el fuera de juego. | F62: Concede el gol y amonesta al defensor por salir del terreno de juego sin permiso del árbitro. | G62: A | H62: A efectos del fuera de juego, si un defensor sale del terreno de juego sin autorización del árbitro, se considera situado en la línea de meta hasta que se detenga el juego o su equipo juegue el balón hacia la línea central y quede fuera de su área. Así, el atacante estaba más cerca de la línea de meta que el balón y que el penúltimo adversario (el guardameta), y participó al recibir el balón: libre indirecto en el lugar de la infracción. | I62: Regla 11.4 / Infracciones y sanciones | J62: 4

Sheet Regla 12
A1: ID | B1: Tipo | C1: Enunciado | D1: Opción A | E1: Opción B | F1: Opción C | G1: Correcta | H1: Explicación | I1: Referencia | J1: Dificultad
A2: RJ12-002 | B2: situacion | C2: Un jugador sale del terreno de juego con la intención de agredir a un espectador. ¿Qué decisión debe tomar el árbitro? | D2: Expulsarlo y reanudar con tiro libre indirecto sobre la línea de demarcación por donde abandonó el terreno de juego. | E2: Expulsarlo y reanudar con balón a tierra en el lugar donde se encontraba el balón cuando se detuvo el juego. | F2: Expulsarlo y reanudar con tiro libre indirecto en el lugar donde se encontraba el balón cuando se detuvo el juego. | G2: A | H2: La conducta violenta fuera del terreno de juego se sanciona con expulsión y reanudación mediante tiro libre indirecto en la línea de demarcación por donde salió el jugador. | I2: Regla 12 | J2: 3
A3: RJ12-003 | B3: situacion | C3: Con el balón en juego, un jugador que recibe atención médica fuera del terreno de juego da una patada con fuerza excesiva a un miembro de su cuerpo técnico. El árbitro... | D3: Lo expulsa y concede un tiro libre directo en el punto más cercano de la línea de demarcación. | E3: Lo amonesta y concede un tiro libre indirecto en el punto más cercano de la línea de demarcación. | F3: Lo expulsa y reanuda con un balón a tierra en el punto más cercano de la línea de demarcación. | G3: A | H3: La conducta violenta (o escupir) contra cualquier persona, también fuera del terreno de juego, con el balón en juego, se sanciona con expulsión y tiro libre directo o penal desde el punto de la línea de demarcación más próximo al lugar de la infracción. | I3: Regla 12 | J3: 3
A4: RJ12-004 | B4: situacion | C4: Desde el área técnica de un equipo se profiere un insulto grave contra el árbitro. Hay varios suplentes y miembros del cuerpo técnico presentes y no se puede identificar al autor. ¿A quién sanciona el árbitro? | D4: Al primer entrenador presente en el área técnica. | E4: A todos los suplentes presentes en el banquillo. | F4: A ningún miembro, porque no se puede identificar al infractor. | G4: A | H4: Cuando alguien ubicado en el área técnica comete una infracción y no se puede identificar al infractor, se sanciona al primer entrenador presente en el área técnica. | I4: Regla 12.4 / Cuerpo técnico | J4: 3
A5: RJ12-005 | B5: situacion | C5: Tras una cesión con el pie de un compañero, el guardameta, presionado por un adversario, intenta despejar con el pie, falla el golpeo y coge el balón con las manos. El árbitro... | D5: Concede un tiro libre indirecto. | E5: Concede un tiro penal y expulsa al guardameta. | F5: Deja que el juego continúe. | G5: C | H5: Regla 12 (pág. 64): no hay infracción si el guardameta toca el balón con las manos después de haberlo golpeado claramente con el pie «(o lo haya intentado)» con el fin de ponerlo en juego. | I5: Regla 12 | J5: 4
A6: RJ12-006 | B6: situacion | C6: Dos jugadores del mismo equipo se golpean entre sí con fuerza excesiva mientras el balón está en juego, sin que exista disputa por el balón. ¿Qué decisión toma el árbitro? | D6: Detiene el juego, expulsa a ambos por juego brusco grave y reanuda con tiro libre directo a favor del equipo adversario. | E6: Detiene el juego, expulsa a ambos por conducta violenta y reanuda con tiro libre directo o penal a favor del adversario en el lugar de la infracción. | F6: Detiene el juego, expulsa a ambos por conducta violenta y reanuda con tiro libre indirecto a favor del adversario en el lugar de la infracción. | G6: B | H6: Golpearse entre compañeros con fuerza excesiva sin disputa del balón se califica como conducta violenta, sancionándose con expulsión de ambos y tiro libre directo o penal (si procede) a favor del adversario. | I6: Regla 12 | J6: 4
A7: RJ12-007 | B7: situacion | C7: Un jugador realiza un pase a un compañero que está en posición de fuera de juego; un adversario intercepta el pase golpeando el balón con la mano de forma intencionada, desviando su trayectoria. ¿Qué decisión toma el árbitro? | D7: Sanciona la mano y amonesta al defensor por evitar un ataque prometedor. | E7: Sanciona la mano y no toma medida disciplinaria contra el defensor. | F7: Sanciona el fuera de juego, por ser previo a la infracción de mano. | G7: B | H7: Al ser el jugador atacante beneficiario del pase quien estaba en posición de fuera de juego, la mano intencionada del defensor se sanciona sin necesidad de medida disciplinaria adicional en este supuesto concreto. | I7: Regla 12 | J7: 4
A8: RJ12-008 | B8: directa | C8: ¿Tiene derecho el capitán de un equipo a protestar una decisión del árbitro? | D8: No, ni el capitán ni ningún otro jugador tienen ese derecho. | E8: Sí, si considera que hay un error claro puede pedir que se rectifique. | F8: Sí, puede exigir al árbitro que le explique cada una de sus decisiones. | G8: A | H8: Ningún jugador, ni siquiera el capitán, tiene derecho reglamentario a protestar las decisiones del árbitro, sin perjuicio del respeto debido. | I8: Regla 12 / Regla 5 | J8: 1
A9: RJ12-009 | B9: situacion | C9: Un jugador sufre una entrada temeraria que conlleva amonestación y un compañero ejecuta rápidamente el tiro libre, creando una clara ocasión de gol; el árbitro no había iniciado el procedimiento de mostrar la tarjeta. El árbitro... | D9: No permite la reanudación hasta pitar después de amonestar al infractor. | E9: Permite la reanudación y amonesta al infractor en la siguiente interrupción. | F9: Permite la reanudación y ya no amonesta al infractor en la siguiente interrupción. | G9: B | H9: Ante una clara ocasión de gol y sin haber iniciado el procedimiento de tarjeta, el árbitro puede aplicar ventaja permitiendo la reanudación rápida, y amonestar igualmente al infractor en la siguiente interrupción. | I9: Regla 5 / Regla 12 | J9: 4
A10: RJ12-010 | B10: situacion | C10: A unos 45 metros de la portería rival, un defensor sujeta a un atacante que avanza con el balón por el centro del campo. Entre el balón y la portería quedan tres defensores más bien colocados. ¿Qué decide el árbitro? | D10: Concede un libre directo y amonesta al defensor por interrumpir un ataque prometedor. | E10: Concede un libre directo y expulsa al defensor por evitar una ocasión manifiesta de gol. | F10: Concede un libre directo sin sanción disciplinaria. | G10: A | H10: Para valorar una ocasión manifiesta de gol se tienen en cuenta la distancia a la portería, la dirección del juego, la probabilidad de mantener o recuperar el balón y la posición y número de defensores. Aquí solo se interrumpe un ataque prometedor: amonestación por conducta antideportiva. | I10: Regla 12.4 / Evitar un gol o una ocasión manifiesta de gol | J10: 3
A11: RJ12-011 | B11: situacion | C11: Un jugador insulta a otro jugador, al árbitro, a un asistente o al cuarto árbitro, con el balón en juego y dentro del terreno de juego. ¿Cómo se reanuda el juego? | D11: Con tiro libre directo o penal donde se cometió la infracción. | E11: Con tiro libre indirecto donde estaba el balón cuando se detuvo el juego. | F11: Con tiro libre indirecto donde se cometió la infracción. | G11: C | H11: El lenguaje ofensivo, injurioso o insultante se sanciona con tiro libre indirecto en el lugar donde se cometió la infracción, junto a la expulsión correspondiente. | I11: Regla 12 | J11: 3
A12: RJ12-012 | B12: situacion | C12: Durante la tanda de penales, un guardameta amonestado durante el partido se encara con el lanzador sin llegar al insulto ni a la amenaza. El árbitro... | D12: Lo amonesta por segunda vez y lo expulsa. | E12: Lo amonesta, sin expulsarlo. | F12: Lo expulsa por conducta violenta. | G12: B | H12: Al iniciarse la tanda de penaltis, las amonestaciones del tiempo reglamentario y prórroga se eliminan a efectos de doble amonestación durante la propia tanda. | I12: Regla 12 / Anexo tandas de penaltis | J12: 4
A13: RJ12-013 | B13: situacion | C13: Un jugador con el balón, siendo sujetado por un adversario, consigue pasar el balón a un compañero que continúa el ataque. ¿Qué decisión toma el árbitro? | D13: Detiene el juego y amonesta al defensor por conducta antideportiva. | E13: Deja que el juego continúe y debe amonestar obligatoriamente al defensor en la siguiente interrupción. | F13: Deja que el juego continúe y, en la siguiente interrupción, amonesta o no según la gravedad, sin obligación automática. | G13: C | H13: Si el ataque continúa pese a la sujeción, se aplica ventaja y, en la siguiente interrupción, el árbitro decide si amonesta según la gravedad de la infracción, sin ser obligatorio automáticamente. | I13: Regla 12 | J13: 3
... A203: RJ12-250 | B203: situacion | C203: El guardameta controla el balón con las manos dentro de su propia área durante más de ocho segundos antes de soltarlo, tras haber efectuado el árbitro la cuenta atrás de los últimos cinco segundos con la mano alzada. ¿Qué decisión toma el árbitro? | D203: Concede un saque de esquina al equipo adversario, sin sanción disciplinaria para el guardameta. | E203: Concede un tiro libre indirecto al equipo adversario, sin sanción disciplinaria para el guardameta. | F203: Concede un saque de esquina al equipo adversario y amonesta al guardameta por retrasar la reanudación. | G203: A | H203: Se concederá un saque de esquina si el guardameta, dentro de su propia área, controla el balón con las manos o los brazos durante más de ocho segundos antes de soltarlo. La Regla 12.3 no prevé sanción disciplinaria por ello. | I203: Regla 12.3 / Ocho segundos | J203: 2

Sheet Regla 13
A1: ID | B1: Tipo | C1: Enunciado | D1: Opción A | E1: Opción B | F1: Opción C | G1: Correcta | H1: Explicación | I1: Referencia | J1: Dificultad
A2: RJ13-001 | B2: situacion | C2: Un jugador, que no es el guardameta, ejecuta un tiro libre fuera del área y toca el balón por segunda vez de forma involuntaria antes de que lo toque otro jugador. Decisión: | D2: El árbitro ordenará repetir el tiro libre, al tratarse de un toque involuntario del ejecutor. | E2: El árbitro aplicará ventaja si procede; si no, concederá un tiro libre indirecto al equipo contrario. | F2: El árbitro dejará que el juego continúe, al no constituir infracción un toque involuntario. | G2: B | H2: El doble toque involuntario del ejecutor se sanciona con tiro libre indirecto al equipo contrario, aplicando ventaja si es posible antes de detener el juego. | I2: Regla 13 | J2: 4
A3: RJ13-002 | B3: situacion | C3: Un jugador ejecuta rápidamente un tiro libre y un adversario situado a 5 metros intercepta el balón. Decisión del árbitro: | D3: Ordena repetir el tiro libre y amonesta al adversario. | E3: Ordena repetir el tiro libre. | F3: Deja que el juego continúe. | G3: C | H3: Regla 13 (pág. 72): si un jugador ejecuta un tiro libre rápido y un adversario a menos de 9,15 m intercepta el balón, el árbitro permitirá que el juego continúe. | I3: Regla 13 | J3: 2
A4: RJ13-005 | B4: situacion | C4: En la ejecución de un tiro libre directo a favor del equipo atacante fuera del área, ¿a qué distancia mínima deben situarse los adversarios del balón, salvo que estén sobre su propia línea de meta entre los postes? | D4: 5 metros. | E4: 7,32 metros. | F4: 9,15 metros. | G4: C | H4: La distancia reglamentaria mínima que deben guardar los adversarios en los tiros libres es de 9,15 metros, salvo excepciones específicas junto a la propia meta. | I4: Regla 13 | J4: 2
A5: RJ13-007 | B5: directa | C5: ¿Hasta cuándo mantiene el árbitro la señal de tiro libre indirecto? | D5: Hasta que se ejecuta el tiro y el balón toca a otro jugador, deja de estar en juego o es evidente que no puede marcarse gol directamente. | E5: Hasta que se ejecuta el tiro y el balón toca a un jugador adversario, sin otros supuestos posibles. | F5: Hasta que el balón esté en juego tras ser golpeado con el pie y se mueva con claridad, sin otros supuestos posibles. | G5: A | H5: La señal se mantiene hasta que se ejecuta el tiro y el balón toca a otro jugador, deja de estar en juego o está claro que no es posible marcar gol directamente. | I5: Regla 13.1 / Señal de tiro libre indirecto | J5: 2
A6: RJ13-008 | B6: situacion | C6: El árbitro concede un tiro libre indirecto, pero olvida levantar el brazo. El ejecutor golpea el balón y este entra directamente en la portería contraria sin tocar a nadie. ¿Qué decisión toma el árbitro? | D6: Ordena repetir el tiro libre, al haber olvidado señalar que era indirecto. | E6: Concede saque de meta a favor del equipo defensor, al ser un tiro libre indirecto. | F6: Concede gol, ya que el error de señalización es del árbitro. | G6: A | H6: Si el árbitro olvida indicar que el tiro es indirecto y el balón entra directamente en la portería, se repite el tiro. | I6: Regla 13.1 / Señal de tiro libre indirecto | J6: 2
A7: RJ13-012 | B7: situacion | C7: Dentro de su área de meta, un defensor obstaculiza sin contacto a un atacante. ¿Desde dónde se ejecuta el tiro libre indirecto a favor del equipo atacante? | D7: Desde el punto más cercano de la línea del área de meta paralela a la línea de meta. | E7: Desde el punto exacto donde se cometió la infracción, dentro del área de meta. | F7: Desde el punto más cercano de la línea del área penal paralela a la línea de meta. | G7: A | H7: Cuando corresponde un tiro libre indirecto a favor del equipo atacante por una infracción cometida dentro del área de meta, se ejecuta desde el punto de la línea del área de meta (paralela a la línea de meta) más próximo al lugar donde se produjo la infracción. | I7: Regla 13.2 / Procedimiento | J7: 3
A8: RJ13-014 | B8: situacion | C8: El equipo defensor tiene un tiro libre a su favor dentro de su propia área de meta. ¿Desde qué lugar puede ejecutarse? | D8: Desde cualquier punto del área de meta. | E8: Desde el lugar exacto de la infracción. | F8: Desde el punto más próximo al banderín de esquina. | G8: A | H8: Los tiros libres a favor del equipo defensor en su área de meta podrán ejecutarse desde cualquier punto de dicha área. | I8: Regla 13.2 / Procedimiento | J8: 2
A9: RJ13-015 | B9: situacion | C9: Un jugador vuelve a entrar en el terreno de juego sin permiso del árbitro, que detiene el juego para sancionarlo, sin que haya habido interferencia. ¿Desde dónde se ejecuta el tiro libre? | D9: Desde el lugar donde se encontraba el balón cuando se detuvo el juego. | E9: Desde el punto de la línea de demarcación por donde entró el jugador. | F9: Desde el punto central del terreno de juego. | G9: A | H9: Los libres por entrada, reingreso o salida sin permiso se ejecutan desde el lugar donde estaba el balón cuando se detuvo el juego. | I9: Regla 13.2 / Procedimiento | J9: 2
A10: RJ13-016 | B10: situacion | C10: Con el balón en juego, un suplente comete fuera del terreno de juego una infracción física contra un adversario, cerca de la línea de banda. ¿Dónde se ejecuta el tiro libre? | D10: En el lugar donde se encontraba el balón al detenerse el juego. | E10: En el punto de la línea de banda más cercano a su banquillo. | F10: En el punto de la línea de demarcación más cercano a la infracción. | G10: C | H10: Cuando la infracción se comete fuera del terreno de juego, el tiro libre se ejecuta en la línea de demarcación más cercana al lugar de la infracción. | I10: Regla 13.2 / Procedimiento | J10: 3
A11: RJ13-017 | B11: situacion | C11: En un tiro libre, un adversario se sitúa a 5 metros del balón antes de que se ejecute y el árbitro no puede aplicar la ventaja. El árbitro... | D11: Ordena que se vuelva a ejecutar el tiro libre. | E11: Concede un tiro libre indirecto donde estaba el adversario. | F11: Deja que el juego continúe y amonesta al adversario. | G11: A | H11: Si un adversario no respeta la distancia reglamentaria, se vuelve a ejecutar el tiro a menos que pueda concederse ventaja. | I11: Regla 13.3 / Infracciones y sanciones | J11: 2
A12: RJ13-018 | B12: situacion | C12: Un jugador ejecuta rápidamente un tiro libre y un adversario situado a 6 metros, que no había obstaculizado deliberadamente la ejecución, intercepta el balón. El árbitro... | D12: Deja que el juego continúe. | E12: Concede un tiro libre indirecto. | F12: Ordena repetir el tiro libre y amonesta al adversario. | G12: A | H12: En un tiro libre rápido, si un adversario a menos de 9,15 m intercepta el balón, el árbitro permite que el juego continúe. | I12: Regla 13.3 / Infracciones y sanciones | J12: 2
A13: RJ13-019 | B13: situacion | C13: Un jugador ejecuta un tiro libre rápido y un adversario se coloca deliberadamente delante del balón para obstaculizar el saque. ¿Qué decide el árbitro? | D13: Amonesta al adversario por retrasar la reanudación del juego. | E13: Amonesta al adversario por conducta antideportiva y ordena repetir el tiro libre. | F13: Amonesta al adversario por no respetar la distancia reglamentaria. | G13: A | H13: El adversario que obstaculice deliberadamente el saque de un tiro libre rápido será amonestado por retrasar la reanudación. | I13: Regla 13.3 / Infracciones y sanciones | J13: 2
... A46: RJ13-062 | B46: situacion | C46: Tras señalar un tiro libre indirecto, el equipo atacante pide al árbitro reanudar con un balón a tierra porque le resulta más ventajoso. El árbitro... | D46: No accede: la reanudación depende de la infracción cometida. | E46: Accede si el equipo adversario no se opone a esa petición. | F46: Accede si considera que es más ventajoso para el atacante. | G46: A | H46: El tipo de reanudación que corresponde tras una infracción viene determinado por las propias Reglas de Juego según la naturaleza de la infracción; no puede sustituirse por otro distinto a petición de un equipo. | I46: Regla 13 | J46: 3

Sheet Regla 14
A1: ID | B1: Tipo | C1: Enunciado | D1: Opción A | E1: Opción B | F1: Opción C | G1: Correcta | H1: Explicación | I1: Referencia | J1: Dificultad
A2: RJ14-001 | B2: situacion | C2: Tras ejecutarse correctamente un tiro penal, el balón se desplaza hacia adelante y queda defectuoso sin haber tocado a ningún jugador ni al guardameta. ¿Cómo se reanuda el juego? | D2: Con la repetición del tiro penal, al haber quedado defectuoso el balón. | E2: Con un balón a tierra a favor del guardameta dentro de su área. | F2: Con un balón a tierra a favor del ejecutor, por ser el último que tocó el balón. | G2: A | H2: Si el balón queda defectuoso tras un tiro penal correctamente ejecutado, antes de tocar a otro jugador, guardameta o cuerpo extraño, se repite el lanzamiento. | I2: Regla 14 / Glosario | J2: 3
A3: RJ14-002 | B3: situacion | C3: Un defensor ejecuta correctamente un tiro libre indirecto desde su propia área penal, dirigido hacia su guardameta, que se encuentra también dentro del área. El guardameta coge el balón con las manos antes de que entre en la portería. ¿Qué decisión toma el árbitro? | D3: Concede tiro libre indirecto a favor del equipo adversario, sin sanción disciplinaria. | E3: Ordena repetir el tiro libre y amonesta al defensor. | F3: Concede tiro libre indirecto y expulsa al guardameta por evitar una ocasión manifiesta de gol. | G3: A | H3: El guardameta comete infracción al tocar con las manos un pase deliberado de un compañero, sancionándose con tiro libre indirecto sin sanción disciplinaria adicional en este supuesto. | I3: Regla 14 / Regla 12 | J3: 4
A4: RJ14-003 | B4: situacion | C4: Tras un disparo de un atacante, el balón queda defectuoso mientras se dirige a la portería, sin tocar a nadie, y entra en ella. El árbitro... | D4: Concede el gol. | E4: Reanuda con un balón a tierra al guardameta. | F4: Reanuda con un balón a tierra al equipo atacante. | G4: B | H4: Regla 2 (pág. 31): si el balón pierde sus propiedades, se detendrá el juego y se reanudará con un balón a tierra. Regla 8: si el balón está en el área penal, el balón a tierra se concede al guardameta. | I4: Regla 14 / Regla 2 / Regla 10 | J4: 3
A5: RJ14-004 | B5: situacion | C5: Tras el lanzamiento de un penal se produce un rechace, y en ese momento un defensor que había infringido las reglas de juego interfiere en el segundo disparo del atacante. ¿Qué decisión toma el árbitro? | D5: Concede el gol si entra o manda repetir el tiro penal. | E5: Concede el gol si entra o reanuda con tiro libre indirecto. | F5: Manda repetir el tiro penal o reanuda con tiro libre indirecto. | G5: A | H5: Cuando el defensor infringe antes del rechace y luego interfiere en el segundo disparo, el árbitro concede el gol si el balón entra o, en caso contrario, ordena repetir el tiro penal. | I5: Regla 14 | J5: 4
A6: RJ14-005 | B6: situacion | C6: En un tiro penal, el ejecutor golpea el balón de forma involuntaria con los dos pies a la vez, o el balón le toca la pierna de apoyo justo después del golpeo, y el balón entra directamente en la portería. El árbitro... | D6: Ordena repetir el tiro penal. | E6: Concede el gol. | F6: Concede un tiro libre indirecto al equipo defensor. | G6: A | H6: Si el lanzador del penal golpea el balón de manera involuntaria con los dos pies simultáneamente, o el balón le toca el pie o la pierna de apoyo justo después de ejecutar el tiro, y el balón entra directamente en la portería, se repite el penal. | I6: Regla 14 | J6: 3
A7: RJ14-006 | B7: directa | C7: ¿Cuál es la posición correcta del árbitro asistente durante la ejecución de un tiro penal? | D7: En la intersección de la línea de meta con el área penal, o a la altura del punto de penalti en la línea de banda. | E7: Detrás del banderín de esquina, siguiendo la misma referencia que en un saque de esquina del equipo defensor. | F7: En la intersección de la línea de meta con el área de meta, controlando la posición del guardameta. | G7: A | H7: Durante un tiro penal, el asistente se sitúa en la intersección de la línea de meta y el área penal, o a la altura del punto de penalti sobre la línea de banda. | I7: Regla 14 | J7: 1
A8: RJ14-007 | B8: situacion | C8: En la ejecución de un tiro penal, ¿dónde deben situarse todos los jugadores excepto el ejecutor y el guardameta? | D8: Fuera del área penal, detrás del punto de penal y a al menos 9,15 metros de dicho punto. | E8: Dentro del área penal, a más de 5 metros del punto de penal. | F8: En cualquier lugar del terreno de juego, si no están dentro del círculo central. | G8: A | H8: En un tiro penal, el resto de jugadores deben permanecer fuera del área penal, detrás del punto de penal y a una distancia mínima de 9,15 metros de este. | I8: Regla 14 | J8: 2
A9: RJ14-008 | B9: directa | C9: ¿Por qué tipo de infracción se concede un tiro penal? | D9: Por una infracción sancionable con libre directo cometida por un jugador dentro de su propia área penal. | E9: Por cualquier infracción, directa o indirecta, cometida por un jugador dentro de su propia área penal. | F9: Por una infracción sancionable con libre directo cometida en cualquier punto de su propia mitad del campo. | G9: A | H9: Se concede penal siempre que un jugador cometa una infracción sancionable con libre directo dentro de su área penal o fuera del terreno de juego como parte del juego. | I9: Regla 14 / Introducción | J9: 1
A10: RJ14-012 | B10: directa | C10: ¿Dónde debe situarse el guardameta defensor hasta el golpeo del balón en un tiro penal? | D10: A un máximo de un metro por delante de la línea de meta. | E10: Sobre la línea del área de meta, frente al ejecutor. | F10: Sobre su línea de meta, entre los postes y frente al ejecutor. | G10: C | H10: El guardameta deberá permanecer sobre su propia línea de meta, entre los postes y frente al ejecutor hasta el golpeo. | I10: Regla 14.1 / Procedimiento | J10: 1
A11: RJ14-013 | B11: situacion | C11: Antes del golpeo de un tiro penal, el guardameta toca el travesaño para distraer al ejecutor, y el balón entra en la portería. El árbitro... | D11: Concede el gol. | E11: Ordena repetir el tiro penal. | F11: Concede un tiro libre indirecto. | G11: A | H11: Si el guardameta comete una infracción y el balón entra en la portería, se concede gol. | I11: Regla 14.2 / Infracciones y sanciones | J11: 2
A12: RJ14-014 | B12: situacion | C12: Antes del golpeo de un tiro penal, el guardameta avanza con los dos pies delante de la línea de meta y detiene el lanzamiento. Es la primera infracción del guardameta en el partido. ¿Qué decide el árbitro? | D12: Ordena repetir el penal y advierte al guardameta. | E12: Ordena repetir el penal y amonesta al guardameta. | F12: Concede un tiro libre indirecto a favor del equipo atacante. | G12: A | H12: Si el guardameta evita el gol con su infracción se repite el penal; se advierte en la primera infracción y se amonesta en la reincidencia. | I12: Regla 14.2 / Infracciones y sanciones | J12: 2
A13: RJ14-015 | B13: situacion | C13: Antes del golpeo de un penal, el guardameta, que ya había sido advertido por una infracción anterior en el partido, se adelanta de la línea y detiene el lanzamiento. ¿Qué decide el árbitro? | D13: Ordena repetir el penal y advierte de nuevo al guardameta. | E13: Ordena repetir el penal y amonesta al guardameta. | F13: Concede gol y amonesta al guardameta. | G13: B | H13: Si la infracción conlleva repetición, se advierte al guardameta en la primera infracción y se le amonesta en caso de reincidencia. | I13: Regla 14.2 / Infracciones y sanciones | J13: 3
... A57: RJ14-073 | B57: situacion | C57: Durante la ejecución de un tiro penal, el ejecutor golpea el balón de manera involuntaria con los dos pies a la vez, o el balón le toca el pie o la pierna de apoyo justo después de ejecutar el tiro, y el balón no entra directamente en la portería (por ejemplo, sale fuera o lo detiene el guardameta). ¿Qué decide el árbitro? | D57: Concede un tiro libre indirecto a favor del equipo defensor. | E57: Ordena repetir el tiro penal, al tratarse de un toque involuntario. | F57: Registra el lanzamiento como fallado y el juego continúa con un saque de meta. | G57: A | H57: Si el lanzador golpea el balón de manera involuntaria con los dos pies simultáneamente, o el balón le toca el pie o la pierna de apoyo justo después del tiro, y el balón no entra directamente en la portería, se concede un tiro libre indirecto (si entra, se repite el penal). | I57: Regla 14 | J57: 3

Sheet Regla 15
A1: ID | B1: Tipo | C1: Enunciado | D1: Opción A | E1: Opción B | F1: Opción C | G1: Correcta | H1: Explicación | I1: Referencia | J1: Dificultad
A2: RJ15-001 | B2: situacion | C2: El entrenador del Equipo A retiene el balón con las manos para evitar un saque de banda rápido de su propio equipo. ¿Qué decisión toma el árbitro? | D2: Amonesta al entrenador por retrasar la puesta del balón en juego. | E2: Expulsa al entrenador por retrasar la puesta del balón en juego. | F2: Realiza únicamente una advertencia verbal al entrenador. | G2: A | H2: Impedir deliberadamente la rápida puesta en juego del balón, incluso por parte de un miembro del cuerpo técnico, se sanciona con amonestación por conducta antideportiva / retraso. | I2: Regla 15 / Regla 12 | J2: 3
A3: RJ15-002 | B3: situacion | C3: Un saque de banda se ejecuta incorrectamente. ¿Puede el árbitro aplicar la ventaja? | D3: Sí, si beneficia al equipo adversario. | E3: No, salvo ocasión manifiesta de gol del adversario. | F3: No, el saque de banda pasa al equipo adversario. | G3: C | H3: Regla 15 (pág. 77): «Si no se ejecutase correctamente, sacará de banda el equipo adversario». | I3: Regla 15 | J3: 1
A4: RJ15-003 | B4: situacion | C4: Un jugador recoge muy lentamente el balón para ejecutar un saque de banda con ánimo de retrasar. ¿Puede el árbitro iniciar la cuenta atrás de cinco segundos aunque el jugador no tenga aún el balón? | D4: Sí, no tiene que esperar a que el jugador esté en posesión del balón. | E4: No, solo puede empezar la cuenta cuando el jugador tenga el balón en las manos. | F4: Solo después de haberle hecho una advertencia con el silbato. | G4: A | H4: El árbitro no tiene que esperar a que el jugador tenga el balón para comenzar la cuenta atrás de cinco segundos si éste provoca un retraso deliberado, por ejemplo recogiendo lentamente el balón o ubicándose incorrectamente. | I4: Protocolo cuenta atrás / Saque de banda | J4: 3
A5: RJ15-004 | B5: directa | C5: ¿A quién se concede el saque de banda cuando el balón atraviesa completamente la línea de banda? | D5: Al equipo del último jugador que tocó el balón. | E5: Al equipo del jugador más cercano al lugar por donde salió el balón. | F5: A los adversarios del último jugador que tocó el balón. | G5: C | H5: El saque de banda se concede a los adversarios del último jugador que tocó el balón antes de que este atravesase totalmente la línea de banda. | I5: Regla 15 / Concesión | J5: 1
A6: RJ15-005 | B6: situacion | C6: Un balón bombeado atraviesa por completo la línea de banda por el aire, sin llegar a tocar el suelo fuera del terreno de juego. El árbitro... | D6: Concede un saque de banda. | E6: Deja que el juego continúe si el viento lo devuelve al campo. | F6: Deja que el juego continúe mientras no toque el suelo fuera. | G6: A | H6: El saque de banda se concede cuando el balón atraviesa totalmente la línea de banda por el suelo o por el aire. | I6: Regla 15 / Concesión | J6: 2
A7: RJ15-006 | B7: situacion | C7: El balón entra directamente en la portería adversaria, sin que lo toque nadie más, tras un saque de banda, tras un tiro libre indirecto o tras un balón a tierra (sin haber tocado a dos jugadores como mínimo). ¿Qué decide el árbitro en todos los casos? | D7: En todos los casos no concede gol y concede saque de meta a favor del equipo defensor. | E7: Concede gol en todos los casos, al haber entrado el balón en la portería. | F7: Concede saque de esquina al equipo atacante en todos los casos. | G7: A | H7: No puede marcarse gol directamente de un saque de banda, de un tiro libre indirecto ni de un balón a tierra sin que el balón haya tocado como mínimo a dos jugadores; si el balón entra en la portería del adversario, se concede saque de meta. | I7: Regla 15 / Concesión | J7: 3
A8: RJ15-007 | B8: situacion | C8: Un jugador ejecuta un saque inicial, un saque de banda, un saque de meta, un saque de esquina o un tiro libre (directo o indirecto), o interviene en un balón a tierra, y el balón entra directamente en su propia portería sin que lo toque nadie más. ¿Qué decide el árbitro en todos los casos? | D8: En todos los casos lo mismo: concede un saque de esquina al equipo adversario. | E8: Concede gol al equipo adversario en todos los casos. | F8: Ordena repetir la reanudación en todos los casos, al no poder marcarse gol en propia meta. | G8: A | H8: Si el balón entra directamente en la propia portería del ejecutor tras un saque inicial, de banda, de meta o de esquina, un tiro libre (directo o indirecto) o un balón a tierra (sin haber tocado a otro jugador), se concede saque de esquina al equipo adversario. | I8: Regla 15 / Concesión | J8: 3
A9: RJ15-008 | B9: directa | C9: ¿Cómo debe lanzar el balón el ejecutor de un saque de banda? | D9: Con ambas manos, desde atrás y por encima de la cabeza, desde el lugar por donde salió. | E9: Con una o ambas manos, desde la altura del pecho, desde cualquier punto de la banda. | F9: Con ambas manos, por encima de la cabeza, desde el punto más cercano al centro del campo. | G9: A | H9: El lanzador deberá lanzar el balón con ambas manos desde atrás y por encima de la cabeza desde el lugar en que el balón salió del campo. | I9: Regla 15.1 / Procedimiento | J9: 1
A10: RJ15-009 | B10: situacion | C10: El árbitro concede el saque de banda al equipo adversario porque el equipo que debía sacar superó la cuenta atrás de cinco segundos. ¿Desde dónde se ejecuta ese saque? | D10: Desde la misma ubicación que tenía el saque de banda original. | E10: Desde el punto de la línea de banda más cercano al balón en ese momento. | F10: Desde el centro de la línea de banda más cercana. | G10: A | H10: Si el balón no está en juego cuando concluye la cuenta atrás, se concede el saque de banda al equipo adversario, que lo efectúa desde la misma ubicación del original. | I10: Protocolo cuenta atrás / Saque de banda | J10: 3
A11: RJ15-010 | B11: situacion | C11: Un jugador ejecuta un saque de banda con los dos pies fuera de la línea de banda, de pie y de cara al terreno de juego. El árbitro... | D11: Deja que el juego continúe. | E11: Concede el saque al adversario. | F11: Ordena repetir el saque de banda. | G11: A | H11: El lanzador puede pisar la línea de banda con los dos pies o estar situado por fuera de la misma. | I11: Regla 15.1 / Procedimiento | J11: 2
A12: RJ15-012 | B12: directa | C12: ¿A qué distancia mínima del lugar de ejecución de un saque de banda deben permanecer los adversarios? | D12: 5 metros. | E12: 3 metros. | F12: 2 metros. | G12: C | H12: Todos los adversarios deberán permanecer a una distancia mínima de 2 m del lugar de la línea de banda donde se vaya a ejecutar el saque. | I12: Regla 15.1 / Procedimiento | J12: 1
A13: RJ15-013 | B13: situacion | C13: Un jugador ejecuta un saque de banda y el balón toca el suelo antes de entrar en el terreno de juego. ¿Qué decide el árbitro? | D13: Ordena repetir el saque de banda desde la misma posición. | E13: Concede el saque de banda al equipo adversario. | F13: Concede un tiro libre indirecto a favor del equipo adversario. | G13: A | H13: Si el balón toca el suelo antes de entrar en el terreno de juego, se repite el saque de banda desde la misma posición. | I13: Regla 15.1 / Procedimiento | J13: 2
... A43: RJ15-051 | B43: situacion | C43: Un saque de banda se ejecuta de forma incorrecta: tras la cuenta atrás de 5 segundos sin sacar, desde un lugar distinto de donde salió el balón, de espaldas al terreno de juego, o con un pie levantado del suelo. ¿Qué decide el árbitro en los cuatro casos? | D43: En los cuatro casos lo mismo: concede el saque de banda al equipo adversario. | E43: Solo se sanciona el retraso tras la cuenta atrás; los demás defectos de ejecución no se sancionan. | F43: Se repite el saque con el mismo equipo en los cuatro casos, sin cederlo al adversario. | G43: A | H43: Cualquier incumplimiento del procedimiento de ejecución de un saque de banda (retraso tras la cuenta atrás, lugar incorrecto, posición incorrecta del cuerpo, no respetar el apoyo de los pies) se sanciona de la misma forma: se concede el saque de banda al equipo adversario. | I43: Regla 15 | J43: 2

Sheet Regla 16
A1: ID | B1: Tipo | C1: Enunciado | D1: Opción A | E1: Opción B | F1: Opción C | G1: Correcta | H1: Explicación | I1: Referencia | J1: Dificultad
A2: RJ16-001 | B2: situacion | C2: Durante un saque de meta, el guardameta eleva el balón para que un compañero se lo devuelva de cabeza y poder cogerlo con las manos. ¿Qué decisión toma el árbitro? | D2: Amonesta al guardameta y concede un tiro libre indirecto al equipo adversario. | E2: Deja que el juego continúe. | F2: Amonesta al compañero que cede el balón y concede un tiro libre indirecto. | G2: A | H2: El intento de burlar la prohibición de la cesión intencionada mediante un artificio (elevar el balón para que otro lo remate de cabeza al guardameta) se sanciona amonestando al guardameta y concediendo tiro libre indirecto. | I2: Regla 16 / Regla 12 | J2: 3
A3: RJ16-002 | B3: situacion | C3: Tras un saque de meta correctamente ejecutado, el guardameta golpea mal el balón, que queda cerca del punto penal, y lo desvía con la mano antes de que un adversario próximo lo juegue, evitando un ataque prometedor. Decisión: | D3: El árbitro concede un tiro libre indirecto y amonesta al guardameta. | E3: El árbitro manda repetir el saque de meta. | F3: El árbitro concede un tiro libre indirecto y expulsa al guardameta. | G3: A | H3: Tocar el balón con la mano fuera del área tras un saque de meta ya en juego, evitando un ataque prometedor, se sanciona con tiro libre indirecto y amonestación (no expulsión, al no ser ocasión manifiesta de gol sino ataque prometedor). | I3: Regla 16 / Regla 12 | J3: 4
A4: RJ16-003 | B4: situacion | C4: Un jugador ejecuta correctamente un saque de meta y, antes de que el balón sea tocado por otro jugador, lo golpea intencionadamente con la mano. ¿Qué decisión toma el árbitro? | D4: Concede tiro libre indirecto, directo o penal según la infracción, con la sanción disciplinaria que corresponda. | E4: Concede tiro libre indirecto a favor del equipo adversario, con o sin sanción disciplinaria según la infracción. | F4: Ordena repetir el saque de meta, sin sanción disciplinaria. | G4: A | H4: Jugar el balón con la mano tras un saque de meta, antes de que otro jugador lo toque, se sanciona según la gravedad: indirecto, directo o penal, con la sanción disciplinaria correspondiente. | I4: Regla 12 / Regla 16 | J4: 3
A5: RJ16-004 | B5: situacion | C5: En un saque de meta, ¿debe el balón salir del área penal para estar en juego? | D5: No, está en juego cuando se golpea y se mueve con claridad. | E5: Sí, está en juego cuando sale del área penal. | F5: No, pero debe salir del área de meta para estar en juego. | G5: A | H5: Según la Regla 16, el balón estará en juego en el momento en que haya sido golpeado con el pie y esté claramente en movimiento; no es necesario que salga del área penal. | I5: Regla 16 | J5: 2
A6: RJ16-005 | B6: situacion | C6: En un saque de meta, el árbitro termina la cuenta atrás de cinco segundos justo cuando el guardameta está golpeando el balón. El árbitro... | D6: Deja que el juego continúe. | E6: Concede un saque de esquina. | F6: Ordena repetir el saque de meta. | G6: A | H6: No se sancionará al jugador si, en el momento en que está lanzando o golpeando el balón, el árbitro concluye la cuenta atrás. | I6: Protocolo cuenta atrás / Saque de meta | J6: 3
A7: RJ16-006 | B7: situacion | C7: Tras un saque inicial, un saque de meta, un saque de esquina o un tiro libre directo, el balón entra directamente en la portería adversaria sin que lo toque nadie más. El árbitro... | D7: Concede el gol en todos los casos. | E7: Concede el gol solo en el tiro libre directo. | F7: No concede el gol en ninguno de los casos. | G7: A | H7: Se puede marcar gol directamente de un saque inicial, de un saque de meta, de un saque de esquina o de un tiro libre directo, siempre contra el equipo adversario. | I7: Regla 16 / Concesión | J7: 2
A8: RJ16-007 | B8: situacion | C8: Un guardameta retrasa un saque de meta y, tras la cuenta atrás de cinco segundos, el árbitro concede un saque de esquina al adversario. ¿Desde qué lado se ejecuta? | D8: Desde el lado más cercano al lugar del saque de meta. | E8: Desde el lado que elija el equipo atacante. | F8: Desde el lado opuesto al lugar del saque de meta. | G8: A | H8: Se concede un saque de esquina al equipo adversario desde el lado del campo más cercano a la ubicación en la que se debía efectuar el saque de meta. | I8: Protocolo cuenta atrás / Saque de meta | J8: 3
A9: RJ16-009 | B9: situacion | C9: Un jugador ejecuta un saque de meta o un saque de esquina con el balón inmóvil y este se mueve con claridad sin salir del área de meta (o del cuadrante de esquina). ¿Qué decide el árbitro? | D9: Considera el balón en juego y permite que el juego continúe. | E9: Ordena repetir el saque, al no haber salido el balón del área de meta o del cuadrante de esquina. | F9: Concede un tiro libre indirecto al equipo adversario por ejecutar incorrectamente el saque. | G9: A | H9: El balón estará en juego en el momento en que haya sido golpeado con el pie y esté claramente en movimiento, sin necesidad de que salga del área de meta o del cuadrante de esquina. | I9: Regla 16.1 / Procedimiento | J9: 2
A10: RJ16-010 | B10: directa | C10: ¿Dónde deben permanecer los adversarios hasta que el balón esté en juego en un saque de meta? | D10: Fuera del área penal hasta que el balón esté en juego. | E10: Fuera del área de meta, pudiendo estar en el área penal. | F10: A 9,15 m del balón, aunque estén en el área penal. | G10: A | H10: Los adversarios deberán permanecer fuera del área penal hasta que el balón esté en juego. | I10: Regla 16.1 / Procedimiento | J10: 1
A11: RJ16-011 | B11: situacion | C11: El equipo defensor ejecuta un saque de meta y un atacante que no tuvo tiempo de salir del área penal sigue dentro de ella, sin tocar el balón. ¿Qué decide el árbitro? | D11: Permite que el juego prosiga. | E11: Ordena repetir el saque de meta. | F11: Concede un tiro libre indirecto a favor del equipo defensor. | G11: A | H11: Si un adversario no ha tenido tiempo de salir del área penal, el árbitro permite que el juego prosiga. | I11: Regla 16.2 / Infracciones y sanciones | J11: 2
A12: RJ16-012 | B12: situacion | C12: En un saque de meta, un atacante toca el balón dentro del área penal antes de que este esté en juego. ¿Qué decide el árbitro? | D12: Concede un tiro libre indirecto a favor del equipo defensor. | E12: Ordena repetir el saque de meta. | F12: Amonesta al atacante y concede un balón a tierra. | G12: B | H12: Si un adversario toca o disputa el balón dentro del área antes de que esté en juego, se repite el saque de meta. | I12: Regla 16.2 / Infracciones y sanciones | J12: 2
A13: RJ16-013 | B13: situacion | C13: Antes de que el balón esté en juego en un saque de meta, un atacante entra en el área penal y comete una infracción contra un defensor. ¿Qué decide el árbitro? | D13: Concede un tiro penal a favor del equipo defensor. | E13: Concede un tiro libre directo a favor del equipo defensor y amonesta al atacante. | F13: Ordena repetir el saque de meta y podrá amonestar o expulsar al infractor según la gravedad. | G13: C | H13: Si un jugador entra en el área penal antes de que el balón esté en juego y comete infracción contra un adversario, se repite el saque y puede sancionarse. | I13: Regla 16.2 / Infracciones y sanciones | J13: 3
... A29: RJ16-045 | B29: situacion | C29: Durante un saque de meta, un adversario situado fuera del área grita repetidamente en el momento de la ejecución para desconcentrar al ejecutor. ¿Puede sancionarlo el árbitro? | D29: Sí, puede amonestarlo por conducta antideportiva si busca distraer al ejecutor. | E29: No, porque se encuentra fuera del área penal en el momento de la ejecución. | F29: Sí, concediendo un tiro libre indirecto al equipo que ejecuta el saque. | G29: A | H29: Distraer deliberadamente al ejecutor de una reanudación, incluido un saque de meta, mediante gritos u otras acciones, puede sancionarse como conducta antideportiva, a criterio del árbitro. | I29: Regla 16 | J29: 3

Sheet Regla 17
A1: ID | B1: Tipo | C1: Enunciado | D1: Opción A | E1: Opción B | F1: Opción C | G1: Correcta | H1: Explicación | I1: Referencia | J1: Dificultad
A2: RJ17-001 | B2: situacion | C2: En un saque de esquina, el balón golpea en un poste y entra en la portería mientras un atacante está delante del guardameta, por detrás del penúltimo defensor. El árbitro... | D2: Concede el gol. | E2: Anula el gol y concede un saque de meta. | F2: Anula el gol y concede un tiro libre indirecto por fuera de juego. | G2: A | H2: Regla 11: no hay infracción por fuera de juego al recibir el balón directamente de un saque de esquina, y en ese momento nadie puede estar más cerca de la línea de meta que el balón, colocado en el cuadrante. El gol es válido. | I2: Regla 11 / Regla 17 | J2: 3
A3: RJ17-002 | B3: situacion | C3: En la ejecución de un saque de esquina, ¿a qué distancia mínima deben situarse los adversarios del balón hasta que esté en juego? | D3: 5 metros. | E3: 7,32 metros. | F3: 9,15 metros. | G3: C | H3: En los saques de esquina, los adversarios deben permanecer a una distancia mínima de 9,15 metros del balón hasta que esté en juego, igual que en los tiros libres. | I3: Regla 17 | J3: 2
A4: RJ17-004 | B4: situacion | C4: Además de cuando el balón sale por la línea de meta tras tocarlo un defensor, ¿qué dos sanciones dan lugar a un saque de esquina? | D4: Que el guardameta controle el balón más de ocho segundos o que un jugador retrase su saque de meta. | E4: Que el guardameta reciba una cesión con el pie o que un jugador retrase un tiro libre. | F4: Que el guardameta suelte el balón y lo vuelva a coger o que un jugador retrase su saque de banda. | G4: A | H4: El árbitro concede saque de esquina si sanciona al guardameta por controlar el balón más de ocho segundos o a un jugador por retrasar su saque de meta. | I4: Regla 17 / Concesión | J4: 3
A5: RJ17-007 | B5: situacion | C5: Un guardameta es sancionado por controlar el balón con las manos más de ocho segundos dentro de su área, en la zona más cercana al banderín derecho. ¿Dónde se coloca el balón? | D5: En el cuadrante de esquina del lado izquierdo, por ser el contrario. | E5: En el punto donde el guardameta soltó el balón. | F5: En el cuadrante de esquina más cercano al lugar que ocupaba el guardameta. | G5: C | H5: El balón se coloca en el cuadrante de esquina más cercano al lugar por el que cruzó la línea o al que ocupaba el guardameta cuando se le sancionó. | I5: Regla 17.1 / Procedimiento | J5: 3
A6: RJ17-008 | B6: directa | C6: ¿Dónde se coloca el balón en un saque de esquina cuando ha cruzado la línea de meta? | D6: En el cuadrante de esquina del lado en el que se encontraba el guardameta. | E6: En el cuadrante de esquina más cercano al lugar por el que cruzó la línea de meta. | F6: En el punto de la línea de meta más cercano a la esquina. | G6: B | H6: El balón se colocará en el cuadrante de esquina más cercano al lugar por el que cruzó la línea de meta. | I6: Regla 17.1 / Procedimiento | J6: 1
A7: RJ17-011 | B7: directa | C7: ¿Está permitido mover el poste del banderín de esquina para facilitar la ejecución de un saque de esquina? | D7: No, no se deberá mover el poste del banderín. | E7: Sí, si lo autoriza el árbitro antes de la ejecución. | F7: Sí, si se vuelve a colocar tras el saque. | G7: A | H7: En la ejecución del saque de esquina no se deberá mover el poste del banderín. | I7: Regla 17.1 / Procedimiento | J7: 2
A8: RJ17-017 | B8: situacion | C8: Un jugador retrasa injustamente la ejecución de un saque de meta de su equipo y el árbitro se lo concede finalmente al equipo adversario tras la cuenta atrás. ¿Con qué saque se reanuda el juego? | D8: Con un saque de esquina a favor del equipo adversario. | E8: Con un saque de meta a favor del equipo adversario. | F8: Con un tiro libre indirecto a favor del equipo adversario. | G8: A | H8: Sancionar a un jugador por retrasar la ejecución de un saque de meta de su equipo es, junto con el balón que cruza la línea de meta tras tocarlo un defensor, una de las causas por las que se concede un saque de esquina. | I8: Regla 17 | J8: 4
A9: RJ17-019 | B9: situacion | C9: Un jugador ejecuta un saque de esquina y el balón, tras rozar levemente el banderín de esquina, continúa su trayectoria hacia el área. ¿Es válido el saque? | D9: Sí, el contacto leve con el banderín no invalida el saque de esquina. | E9: No, cualquier contacto con el banderín obliga a repetir el saque. | F9: No, se concede un saque de meta al equipo defensor por el contacto con el banderín. | G9: A | H9: El poste del banderín de esquina no debe moverse durante la ejecución, pero un contacto leve del balón con él no invalida el saque. | I9: Regla 17 | J9: 2
A10: RJ17-020 | B10: situacion | C10: Antes de un saque de esquina, un defensor se sitúa deliberadamente a menos de 9,15 m del cuadrante de esquina. El árbitro... | D10: Le advierte y, si persiste, lo amonesta. | E10: Lo expulsa por no respetar la distancia. | F10: No puede actuar hasta que se ejecute el saque. | G10: A | H10: Los adversarios deben respetar la distancia mínima de 9,15 m en un saque de esquina; el incumplimiento persistente tras la advertencia del árbitro se sanciona con amonestación. | I10: Regla 17 | J10: 2
A11: RJ17-022 | B11: situacion | C11: Un jugador ejecuta un saque de esquina y, antes de que el balón esté en juego, un adversario situado a menos de 9,15 m lo toca deliberadamente. ¿Qué decide el árbitro? | D11: Ordena repetir el saque y amonesta al adversario. | E11: Concede tiro libre indirecto al equipo atacante. | F11: Concede tiro libre directo al equipo atacante. | G11: A | H11: Regla 17.2: «Si se cometiera cualquier otra infracción de esta regla, se repetirá el saque». No respetar la distancia reglamentaria en un saque de esquina se sanciona con amonestación (Regla 12.3). | I11: Regla 17 | J11: 2
A12: RJ17-025 | B12: directa | C12: ¿Puede ejecutarse rápidamente un saque de esquina antes de que los adversarios se hayan retirado a la distancia reglamentaria? | D12: Sí, puede ejecutarse rápidamente. | E12: No, el árbitro debe autorizarlo antes. | F12: No, debe esperarse a que estén a 9,15 m. | G12: A | H12: Un saque de esquina puede ejecutarse de forma rápida; los adversarios deben cumplir la distancia reglamentaria, pero ello no impide la ejecución inmediata si ya se respeta. | I12: Regla 17 | J12: 2
A13: RJ17-026 | B13: situacion | C13: El ejecutor de un saque de esquina coloca el balón fuera del cuadrante de esquina y lo pone en juego. El árbitro... | D13: Ordena repetir el saque de esquina. | E13: Concede saque de meta al equipo defensor. | F13: Concede tiro libre indirecto al equipo defensor. | G13: A | H13: Regla 17: «El balón se colocará en el cuadrante de esquina más cercano al lugar por el que cruzó la línea de meta». «Si se cometiera cualquier otra infracción de esta regla, se repetirá el saque». | I13: Regla 17.1 | J13: 3
... A25: RJ17-041 | B25: situacion | C25: Antes de ejecutarse un saque de esquina, el árbitro detecta que el balón no cumple las especificaciones de la Regla 2. El árbitro... | D25: Lo sustituye por otro reglamentario antes de la ejecución. | E25: Permite la ejecución, porque ningún equipo lo ha reclamado. | F25: Permite la ejecución y lo sustituye en la siguiente interrupción. | G25: A | H25: El balón debe cumplir en todo momento las especificaciones de la Regla 2; el árbitro debe sustituirlo antes de autorizar la ejecución de cualquier reanudación, incluido un saque de esquina. | I25: Regla 17 | J25: 3

Sheet Glosario
A1: ID | B1: Tipo | C1: Enunciado | D1: Opción A | E1: Opción B | F1: Opción C | G1: Correcta | H1: Explicación | I1: Referencia | J1: Dificultad
A2: GL-001 | B2: directa | C2: Según el Glosario, los dispositivos de detección automática de goles (DAG) informan al árbitro sobre la validez de un gol: | D2: Inmediatamente. | E2: En el lapso de un segundo. | F2: En el lapso de tres segundos. | G2: A | H2: Glosario (pág. 108): «Dispositivos electrónicos que informan inmediatamente al árbitro sobre la validez de un gol, es decir, si el balón ha atravesado completamente la línea de meta. Más información en la Regla n.º 1». | I2: Glosario / Regla 1 | J2: 2
A3: GL-002 | B3: directa | C3: Según el Glosario, el «cuerpo técnico» es el conjunto de miembros oficiales del equipo que, sin contar a los jugadores, figuran en la lista oficial, tales como: | D3: El entrenador, el fisioterapeuta o el médico. | E3: Los suplentes, el entrenador o el médico. | F3: Los directivos que no figuran en la lista. | G3: A | H3: Glosario (pág. 108): «Conjunto de miembros oficiales del equipo que, sin contar a los jugadores, figuran en la lista oficial, tales como el entrenador, el fisioterapeuta o el médico». | I3: Glosario | J3: 2
A4: GL-004 | B4: directa | C4: Según el Glosario, ¿cuál es la definición de 'agente externo'? | D4: Toda persona ajena al equipo arbitral o no inscrita en la lista del equipo, incluyendo también animales, objetos o estructuras. | E4: Toda persona ajena al equipo arbitral o no inscrita en la lista del equipo, sin incluir animales, objetos o estructuras. | F4: Los espectadores y demás personas que invaden el terreno de juego durante el partido, sin incluir objetos. | G4: A | H4: El Glosario define agente externo como cualquier persona ajena al equipo arbitral o no inscrita en la lista del equipo, incluyendo también animales, objetos o estructuras. | I4: Glosario | J4: 1
A5: GL-005 | B5: directa | C5: Según el Glosario, ¿cómo se define «infracción»? | D5: Acción que vulnera las Reglas de Juego, también denominada «falta». | E5: Acción que vulnera las Reglas de Juego, sancionable con expulsión. | F5: Acción intencionada que vulnera las Reglas de Juego, distinta de la «falta». | G5: A | H5: El Glosario define infracción como la acción que vulnera las Reglas de Juego, también denominada «falta». | I5: Glosario / Infracción | J5: 1
A6: GL-006 | B6: directa | C6: Según el Glosario, ¿en qué consiste la regla de los goles marcados fuera de casa? | D6: Método para decidir el ganador de una eliminatoria a doble partido con el mismo número de goles, contando doble los marcados fuera de casa. | E6: Método por el que gana el equipo que jugó como visitante en el partido de ida, si el resultado global queda empatado. | F6: Procedimiento de desempate alternativo a la tanda de penales, que se aplica si ambas competiciones lo acuerdan expresamente. | G6: A | H6: La regla de los goles marcados fuera de casa dilucida al ganador de una eliminatoria a doble partido empatada en goles, contando doble los goles marcados fuera de casa. | I6: Glosario / Goles marcados fuera de casa | J6: 2
A7: GL-007 | B7: directa | C7: Según el Glosario, ¿cómo se define el lenguaje o las acciones ofensivas, insultantes o humillantes y cuál es su sanción? | D7: Expresiones verbales o conductas de carácter denigrante, hiriente o irrespetuoso, sancionables con expulsión. | E7: Expresiones verbales o conductas de carácter denigrante, hiriente o irrespetuoso, sancionables con amonestación. | F7: Conductas físicas de carácter denigrante, sancionables con expulsión, pero no las expresiones verbales. | G7: A | H7: El lenguaje o las acciones ofensivas, insultantes o humillantes son expresiones verbales o conductas denigrantes, hirientes o irrespetuosas, sancionables con expulsión. | I7: Glosario / Lenguaje o acciones ofensivas, insultantes o humillantes | J7: 2
A8: GL-008 | B8: directa | C8: Según el Glosario, la tecnología semiautomatizada para la detección del fuera de juego: | D8: Envía al instante a los VAR información sobre posiciones de fuera de juego y, en su versión avanzada, también a los asistentes. | E8: Sustituye la decisión del árbitro asistente en cualquier jugada de fuera de juego, sin intervención del VAR ni del árbitro. | F8: Informa solo al árbitro principal sobre posiciones de fuera de juego, sin comunicación con el resto del equipo arbitral. | G8: A | H8: Esta tecnología envía información al instante sobre posiciones de fuera de juego a los VAR y, en versión avanzada, también a los árbitros asistentes. | I8: Glosario / Tecnología semiautomatizada para la detección del fuera de juego | J8: 2
A9: GL-009 | B9: directa | C9: Según el Glosario, ¿qué es el sistema electrónico de seguimiento del rendimiento (EPTS)? | D9: Cualquiera de los diferentes dispositivos o sistemas de registro y análisis sobre el rendimiento físico y fisiológico de un jugador. | E9: Dispositivo instalado en el balón para verificar si ha atravesado completamente la línea de meta durante el partido. | F9: Sistema de comunicación entre el árbitro y el VAR durante el proceso de revisión de una jugada dudosa. | G9: A | H9: El EPTS agrupa los dispositivos o sistemas de registro y análisis del rendimiento físico y fisiológico de un jugador. | I9: Glosario / Sistema electrónico de seguimiento del rendimiento (EPTS) | J9: 2
A10: GL-010 | B10: directa | C10: Según el Glosario, ¿cómo se define el «tiro libre directo»? | D10: Golpeo del balón para ejecutar un lanzamiento de falta con el que se puede marcar gol directamente en la portería adversaria sin que el balón toque a ningún otro jugador. | E10: Golpeo del balón para ejecutar un lanzamiento de falta con el que solo se puede marcar gol si otro jugador toca el balón antes de que entre en la portería. | F10: Golpeo del balón ejecutado dentro del área penal propia por el guardameta, sin restricción sobre el toque de otros jugadores. | G10: A | H10: El tiro libre directo permite marcar gol directamente en la portería adversaria sin que el balón toque a ningún otro jugador. | I10: Glosario / Tiro libre directo | J10: 1
A11: GL-011 | B11: directa | C11: Según el Glosario, el «tiro libre indirecto» es un lanzamiento de falta con el que: | D11: Solo se puede marcar gol si otro jugador, de cualquiera de los dos equipos, toca el balón después. | E11: Se puede marcar gol en la portería adversaria sin que ningún otro jugador toque el balón. | F11: Solo se puede marcar gol si otro jugador del equipo que lo ejecuta toca el balón después. | G11: A | H11: El tiro libre indirecto solo permite marcar gol si otro jugador, de cualquiera de los dos equipos, toca el balón después del lanzamiento. | I11: Glosario / Tiro libre indirecto | J11: 1
A12: GL-012 | B12: directa | C12: Según el Glosario, ¿qué conforman los «miembros del equipo arbitral de vídeo»? | D12: El conjunto de VAR y AVAR que asisten al árbitro de conformidad con las Reglas de Juego y el Protocolo del VAR. | E12: El conjunto de árbitros asistentes y árbitros asistentes adicionales que ayudan al árbitro principal dentro del terreno de juego. | F12: El conjunto formado por el técnico de repeticiones y el cuarto árbitro, que asisten al árbitro principal desde la sala de vídeo. | G12: A | H12: Los miembros del equipo arbitral de vídeo son el conjunto de VAR y AVAR que asisten al árbitro conforme a las Reglas de Juego y el Protocolo del VAR. | I12: Glosario / Miembros del equipo arbitral de vídeo | J12: 2
A13: GL-013 | B13: directa | C13: Según el Glosario, ¿qué es la «advertencia»? | D13: Sanción disciplinaria comunicada con tarjeta amarilla y de la que se da parte a la autoridad competente. | E13: Acto por el que el árbitro censura al infractor y lo anota en el acta sin comunicárselo. | F13: Acto por el que el árbitro apercibe y censura verbalmente al infractor, que no recibe sanción alguna por la infracción. | G13: C | H13: El Glosario define la advertencia (o apercibimiento) como censura verbal sin sanción alguna. | I13: Glosario / Advertencia | J13: 2
... A64: GL-084 | B64: situacion | C64: Un jugador interrumpe un ataque prometedor con una infracción sancionable con tiro libre directo, sin evitar una ocasión manifiesta de gol. El árbitro... | D64: Lo amonesta. | E64: Lo expulsa. | F64: No toma medida disciplinaria. | G64: A | H64: Interrumpir un ataque prometedor mediante una infracción sancionable con tiro libre, sin llegar a evitar una ocasión manifiesta de gol, se sanciona con amonestación por conducta antideportiva, reservándose la expulsión para los casos en que sí se evita una ocasión manifiesta de gol. | I64: Glosario | J64: 3

Sheet VAR
A1: ID | B1: Tipo | C1: Enunciado | D1: Opción A | E1: Opción B | F1: Opción C | G1: Correcta | H1: Explicación | I1: Referencia | J1: Dificultad
A2: VAR-001 | B2: situacion | C2: Un jugador marca un gol; un adversario solicita gesticulando la revisión del VAR por una falta previa y, por ello, el árbitro lo amonesta. Instantes después, el VAR anula el gol. ¿Debe el árbitro retirar la amonestación al no subir el gol al marcador? | D2: No, la amonestación se mantiene aunque el gol se anule. | E2: Sí, al anularse el gol la tarjeta debe anularse también. | F2: Depende de si el jugador celebró el gol de forma provocadora o no. | G2: A | H2: La amonestación por solicitar de forma inapropiada la revisión del VAR se mantiene con independencia de que el gol acabe siendo anulado. | I2: Regla 5 / Protocolo VAR | J2: 4
A3: VAR-002 | B3: directa | C3: Según las Reglas de Juego 2026/27, el VAR puede asistir al árbitro ante un error claro, obvio y manifiesto o un incidente grave inadvertido en relación con: | D3: Gol/no gol, penal/no penal, tarjeta roja (incluida una segunda amonestación claramente incorrecta) y confusión de identidad. | E3: Cualquier decisión dudosa, incluidas las amonestaciones, aunque no exista un error claro, obvio y manifiesto. | F3: Gol/no gol y fuera de juego, aunque no exista un error claro, obvio y manifiesto. | G3: A | H3: Regla 5.4: gol/no gol; penal/no penal; «tarjeta roja (incluida una segunda amonestación claramente incorrecta)»; confusión de identidad; y, si la competición lo prevé, un saque de esquina concedido de forma claramente errónea. | I3: Regla 5.4 / Protocolo del VAR | J3: 2
A4: VAR-003 | B4: directa | C4: Según el Protocolo del VAR, ¿puede el árbitro no tomar una decisión para que la tome después el VAR? | D4: No, debe tomar siempre una decisión inicial. | E4: Sí, en las jugadas de fuera de juego. | F4: Sí, si la jugada es muy compleja. | G4: A | H4: El árbitro no puede omitir una decisión y recurrir después al VAR; debe tomar siempre una decisión inicial. | I4: Protocolo del VAR / Principios | J4: 2
A5: VAR-004 | B5: directa | C5: ¿Cuándo se modifica la decisión inicial del árbitro tras un chequeo del VAR? | D5: Si la revisión demuestra claramente que constituyó un error claro, obvio y manifiesto. | E5: Si el VAR lo recomienda y el árbitro está de acuerdo, aunque el error no sea claro. | F5: Si las imágenes muestran una decisión distinta a la que tomó el árbitro. | G5: A | H5: La decisión inicial no se modifica salvo que la revisión demuestre un error claro, obvio y manifiesto. | I5: Protocolo del VAR / Principios | J5: 2
A6: VAR-005 | B6: directa | C6: ¿Quién puede iniciar una revisión según el Protocolo del VAR? | D6: El árbitro; el VAR y el resto del equipo arbitral pueden recomendarla. | E6: El VAR, que puede imponerla al árbitro cuando detecta un error. | F6: El capitán de cualquiera de los dos equipos, una vez por parte. | G6: A | H6: Solo el árbitro puede iniciar una revisión; el VAR y los demás miembros del equipo arbitral pueden recomendarla. | I6: Protocolo del VAR / Principios | J6: 1
A7: VAR-007 | B7: directa | C7: ¿Existe un tiempo máximo para el proceso de revisión? | D7: No, porque la precisión es más importante que la rapidez. | E7: Sí, un máximo de dos minutos por revisión. | F7: Sí, un máximo de un minuto si es revisión basada en el VAR. | G7: A | H7: No hay límite de tiempo para la revisión, ya que la precisión es más importante que la rapidez. | I7: Protocolo del VAR / Principios | J7: 2
A8: VAR-008 | B8: situacion | C8: Mientras el árbitro realiza una revisión, varios jugadores del equipo perjudicado le rodean para protestar. Según el Protocolo del VAR: | D8: Los jugadores no deben rodear al árbitro ni intentar influir en la revisión. | E8: Los jugadores pueden rodear al árbitro si no llegan a hablar con él. | F8: Solo el capitán puede acompañar al árbitro durante la revisión. | G8: A | H8: Los jugadores y el cuerpo técnico no deberán rodear al árbitro ni intentarán influir en su decisión ni en el proceso de revisión. | I8: Protocolo del VAR / Principios | J8: 2
A9: VAR-009 | B9: situacion | C9: Durante el proceso de revisión, ¿dónde deben permanecer los jugadores y dónde los suplentes y el cuerpo técnico? | D9: Los jugadores en sus áreas de penal; los suplentes y el cuerpo técnico, en el área técnica. | E9: Los jugadores en el terreno de juego; los suplentes y el cuerpo técnico, fuera de él. | F9: Todos en el terreno de juego, hasta que el árbitro adopte la decisión final. | G9: B | H9: Durante la revisión, los jugadores deben permanecer en el terreno y los suplentes y cuerpo técnico fuera del mismo. | I9: Protocolo del VAR / Jugadores, suplentes y cuerpo técnico | J9: 2
A10: VAR-010 | B10: directa | C10: ¿Debe el árbitro permanecer visible durante el proceso de revisión? | D10: Sí, debe permanecer visible durante el proceso, para garantizar la transparencia. | E10: Sí, debe permanecer visible, aunque solo si la revisión es en el terreno de juego. | F10: No, puede retirarse al vestuario mientras se revisa la jugada. | G10: A | H10: El árbitro debe permanecer visible durante la revisión para garantizar la transparencia. | I10: Protocolo del VAR / Principios | J10: 2
A11: VAR-011 | B11: situacion | C11: Si el juego prosigue tras un incidente que se revisa después, ¿se cancela la medida disciplinaria tomada tras ese incidente aunque se modifique la decisión inicial? | D11: No, salvo la amonestación o expulsión por detener un ataque prometedor o evitar una ocasión manifiesta de gol. | E11: Sí, en todos los casos, al modificarse la decisión inicial del árbitro. | F11: No, aunque la sanción fuera por evitar una ocasión manifiesta de gol o detener un ataque prometedor. | G11: A | H11: Si el juego prosigue tras el incidente, no se cancela la medida disciplinaria, salvo la amonestación o expulsión por detener un ataque prometedor o evitar una ocasión manifiesta de gol. | I11: Protocolo del VAR / Principios | J11: 4
A12: VAR-012 | B12: situacion | C12: Una vez reanudado el juego, ¿en qué casos puede el árbitro llevar a cabo una revisión? | D12: En confusión de identidad o posible expulsión por conducta violenta, escupir, morder o actuar de forma extremadamente ofensiva. | E12: En cualquier penal no señalado o gol anulado, sea cual sea el tiempo transcurrido desde la reanudación del juego. | F12: En cualquier tarjeta roja, amarilla o confusión de identidad, aunque el juego ya se haya reanudado tras la decisión. | G12: A | H12: Reanudado el juego, solo se revisa por confusión de identidad o infracción de expulsión por conducta violenta, escupir, morder o actuar de forma extremadamente ofensiva. | I12: Protocolo del VAR / Principios | J12: 4
A13: VAR-013 | B13: directa | C13: ¿Es necesario que los entrenadores o jugadores soliciten una revisión al VAR? | D13: No, porque los VAR chequean automáticamente todas las situaciones o decisiones. | E13: Sí, mediante la señal de la televisión de un jugador o entrenador al árbitro. | F13: Sí, mediante una solicitud del capitán de cada equipo al árbitro. | G13: A | H13: No es necesario solicitar la revisión, pues el VAR chequea automáticamente las situaciones. | I13: Protocolo del VAR / Principios | J13: 1
... A58: VAR-058 | B58: directa | C58: ¿Puede modificarse, durante el propio partido, la decisión de utilizar o no el sistema VAR ya anunciada antes de su inicio? | D58: No, se determina antes del partido conforme a los requisitos exigidos, salvo avería del sistema. | E58: Sí, cualquiera de los dos equipos puede pedir activar o desactivar el VAR durante el partido. | F58: Sí, el árbitro puede decidir libremente activar el VAR en el segundo tiempo. | G58: A | H58: La implementación del VAR se decide antes del inicio del partido conforme a los requisitos técnicos exigidos, sin que pueda modificarse a mitad de encuentro salvo por causas técnicas como una avería. | I58: Protocolo del VAR | J58: 2
